Workbook

Sheet README
B1: McDonald's (MCD) equity research model - v6
B3: Purpose | C3: Valuation model behind the equity research report: Hold, target $249 (DCF 60% / franchise-heavy comps 40%). Every market input is the official 24-Sep-2026 close.
B4: Model flow | C4: Reference_Data and Historical_5Y -> Forecast -> DCF. Market_WACC and Peers -> Comps -> WACC (bottom-up beta) -> DCF. DCF and Comps -> Valuation (target, rating, sensitivities).
B5: How to use | C5: Change blue-on-yellow assumptions on Forecast, WACC and Valuation; everything else recalculates. Model_Review records every change and why.
B10: Legend
B11: 1,234 | C11: Blue text on yellow = input you type
B12: 1,234 | C12: Black = formula, do not overwrite
B13: 1,234 | C13: Green = direct link to another sheet
C14: Grey = not disclosed for that period
B15: 1,234 | C15: Blue text (no fill) = market data or a figure typed from the source in the note column
B16: Label | C16: Lavender label = changed after the 25-26 Sep reviews (see Model_Review)
B17: Conventions | C17: $ in millions unless stated. Percentages entered as decimals (2.1% = 0.021). Costs, capex, buybacks and dividends entered as positive numbers. Q2 = three months to 30 June; H1 = six months to 30 June.
B18: Data notes | C18: Quarterly totals can differ by $1m from the release because line items are rounded. Q2 systemwide sales ($37bn) and loyalty users (~210m, ~220m) are rounded as disclosed. 2023 special charges are not given in the 2025 10-K.
B20: Tabs (in workbook order)
B21: Historical_5Y | C21: FY2021-FY2025 revenue split, operating income, net income, EPS, D&A, capex, FCF, dividends, debt and leverage.
B22: Historical_Drivers | C22: FY2023-H1 2026 operating drivers (comps, units, systemwide sales, take rates, margins, SG&A, FCF conversion, reported ROIC, leverage) and a GAAP-to-adjusted bridge.
B23: Industry_Evidence | C23: Independent U.S. restaurant traffic data (RMS, Black Box, NRA, BLS, Circana, Placer.ai) and franchisee unit economics from Investor Day.
B24: Market_WACC | C24: MCD share price, shares, market cap, raw beta, 10-year Treasury and dividend (24-Sep-2026 close); source multiples and an EV cross-check.
B25: Peers | C25: YUM, QSR, SBUX, CMG, DPZ at the 24-Sep close: market cap, EV, P/E, EV/EBITDA, beta; medians; source snapshot kept as memo.
B26: Forecast | C26: FY2026E-FY2030E, one assumption per line, incl. recurring restructuring; UFCF and company-definition FCF conversion.
B27: Comps | C27: Lease-adjusted peer multiples, unlevered betas, franchise-heavy primary set, implied value, 50/50 rationale, growth table.
B28: WACC | C28: Primary bottom-up beta from franchise-heavy peers (0.60), cost of equity and debt, sensitivities, beta reconciliation, MCD unlevered beta.
B29: DCF | C29: Stub from the 30-Jun-2026 balance sheet, mid-year convention, normalised terminal year, guide checks.
B30: Valuation | C30: 60/40 target, rating (exact bands), football field, WACC vs growth grids, beta check, scenarios, reverse DCF, consensus and comps-weighting checks.
B31: Model_Review | C31: Guide review and five feedback rounds: each point, whether it was right, what changed, target bridges.
B32: Reference_Data | C32: Figures from the 2025 10-K and the Q2 2026 release, with page references; feeds Historical_Drivers, Comps and Forecast.

Sheet Valuation
A1: Target price - blended DCF and comps, football field and sensitivities
A2: Blue on yellow = assumption. Sensitivity cells recompute the full DCF (stub, mid-year, normalised terminal year) for each WACC / growth pair.
A4: Item | B4: Value | C4: Unit | H4: Note
A5: DCF value per share | B5: =DCF!B50 -> 248.87212 | C5: $ | H5: DCF tab
A6: Comps value per share | B6: =Comps!D31 -> 248.13575 | C6: $ | H6: Comps tab: franchise-heavy peers (YUM, QSR, DPZ), 50% forward P/E + 50% LTM EV/EBITDA. REVISED (feedback): was the all-peer median ($292.69).
A7: Weight on DCF | B7: 0.6 | C7: % | H7: Your 60/40 split. Consistent with the guide: the DCF is the primary method, comps are the cross-check.
A8: Weight on comps | B8: =1-B7 -> 0.4 | C8: %
A9: Target price (blended) | B9: =B5*B7+B6*B8 -> 248.57757 | C9: $
A10: Current share price | B10: =Market_WACC!B6 -> 237.02 | C10: $ | H10: 24-Sep-2026 official close (Stock Analysis / S&P Global). REVISED (feedback): was a $240.09 intraday print.
A11: Upside / (downside) to target | B11: =B9/B10-1 -> 0.048762 | C11: % | H11: The guide cautions that gaps of ~10-15% are within the margin of error of any valuation.
A12: Dividend yield | B12: =Market_WACC!B17 -> 0.032571091 | C12: %
A13: Expected total return (upside + yield) | B13: =B11+B12 -> 0.081333091 | C13: %
A14: Rating under the report framework | B14: =IF(B13>=B48,"Buy",IF(B13<=B50,"Sell","Hold")) -> Hold | H14: Bands in B48 and B50: Buy >= +10%, Sell <= -10%, Hold in between.
A15: FOOTBALL FIELD ($ per share) - DCF guide Key Rule #10
A16: Methodology | B16: Low | C16: Base | D16: High | H16: Range definition
A17: DCF (WACC +/- 0.5%, g +/- 0.5%) | B17: =MIN(D24:F26) -> 203.20742 | C17: =DCF!B50 -> 248.87212 | D17: =MAX(D24:F26) -> 316.97121 | H17: Inner 3x3 of the DCF sensitivity grid below.
A18: Comps: forward P/E | B18: =Comps!C29 -> 193.29336 | C18: =Comps!D29 -> 223.07439 | D18: =Comps!E29 -> 287.901 | H18: Franchise-heavy peers: min / median / max forward P/E x MCD NTM EPS.
A19: Comps: LTM EV/EBITDA (lease-adjusted) | B19: =Comps!C30 -> 246.34636 | C19: =Comps!D30 -> 273.1971 | D19: =Comps!E30 -> 289.07563 | H19: Franchise-heavy peers: min / median / max LTM EV/EBITDA x MCD LTM EBITDA.
A20: Current share price | B20: =Market_WACC!B6 -> 237.02 | C20: =Market_WACC!B6 -> 237.02 | D20: =Market_WACC!B6 -> 237.02 | H20: 24-Sep-2026 close
A21: DCF VALUE PER SHARE ($) - WACC vs TERMINAL GROWTH
A22: WACC (rows) \ terminal growth (columns) | C22: =DCF!$B$8+(-2)*$B$44 -> 0.015 | D22: =DCF!$B$8+(-1)*$B$44 -> 0.02 | E22: =DCF!$B$8+(0)*$B$44 -> 0.025 | F22: =DCF!$B$8+(1)*$B$44 -> 0.03 | G22: =DCF!$B$8+(2)*$B$44 -> 0.035
B23: =DCF!$B$7+(-2)*$B$43 -> 0.065573866 | C23: =IF($B23<=C$22,"n/a",(SUMPRODUCT(DCF!$D$23:$H$23/(1+$B23)^DCF!$D$25:$H$25)+DCF!$H$20*(1+C$22)*DCF!$B$35/($B23-C$22)/(1+$B23)^DCF!$B$38-DCF!$B$13)/DCF!$B$15) -> 256.27116 | D23: =IF($B23<=D$22,"n/a",(SUMPRODUCT(DCF!$D$23:$H$23/(1+$B23)^DCF!$D$25:$H$25)+DCF!$H$20*(1+D$22)*DCF!$B$35/($B23-D$22)/(1+$B23)^DCF!$B$38-DCF!$B$13)/DCF!$B$15) -> 285.32706 | E23: =IF($B23<=E$22,"n/a",(SUMPRODUCT(DCF!$D$23:$H$23/(1+$B23)^DCF!$D$25:$H$25)+DCF!$H$20*(1+E$22)*DCF!$B$35/($B23-E$22)/(1+$B23)^DCF!$B$38-DCF!$B$13)/DCF!$B$15) -> 321.54419 | F23: =IF($B23<=F$22,"n/a",(SUMPRODUCT(DCF!$D$23:$H$23/(1+$B23)^DCF!$D$25:$H$25)+DCF!$H$20*(1+F$22)*DCF!$B$35/($B23-F$22)/(1+$B23)^DCF!$B$38-DCF!$B$13)/DCF!$B$15) -> 367.94214 | G23: =IF($B23<=G$22,"n/a",(SUMPRODUCT(DCF!$D$23:$H$23/(1+$B23)^DCF!$D$25:$H$25)+DCF!$H$20*(1+G$22)*DCF!$B$35/($B23-G$22)/(1+$B23)^DCF!$B$38-DCF!$B$13)/DCF!$B$15) -> 429.51578
B24: =DCF!$B$7+(-1)*$B$43 -> 0.070573866 | C24: =IF($B24<=C$22,"n/a",(SUMPRODUCT(DCF!$D$23:$H$23/(1+$B24)^DCF!$D$25:$H$25)+DCF!$H$20*(1+C$22)*DCF!$B$35/($B24-C$22)/(1+$B24)^DCF!$B$38-DCF!$B$13)/DCF!$B$15) -> 229.01907 | D24: =IF($B24<=D$22,"n/a",(SUMPRODUCT(DCF!$D$23:$H$23/(1+$B24)^DCF!$D$25:$H$25)+DCF!$H$20*(1+D$22)*DCF!$B$35/($B24-D$22)/(1+$B24)^DCF!$B$38-DCF!$B$13)/DCF!$B$15) -> 252.53951 | E24: =IF($B24<=E$22,"n/a",(SUMPRODUCT(DCF!$D$23:$H$23/(1+$B24)^DCF!$D$25:$H$25)+DCF!$H$20*(1+E$22)*DCF!$B$35/($B24-E$22)/(1+$B24)^DCF!$B$38-DCF!$B$13)/DCF!$B$15) -> 281.2209 | F24: =IF($B24<=F$22,"n/a",(SUMPRODUCT(DCF!$D$23:$H$23/(1+$B24)^DCF!$D$25:$H$25)+DCF!$H$20*(1+F$22)*DCF!$B$35/($B24-F$22)/(1+$B24)^DCF!$B$38-DCF!$B$13)/DCF!$B$15) -> 316.97121 | G24: =IF($B24<=G$22,"n/a",(SUMPRODUCT(DCF!$D$23:$H$23/(1+$B24)^DCF!$D$25:$H$25)+DCF!$H$20*(1+G$22)*DCF!$B$35/($B24-G$22)/(1+$B24)^DCF!$B$38-DCF!$B$13)/DCF!$B$15) -> 362.77113
B25: =DCF!$B$7+(0)*$B$43 -> 0.075573866 | C25: =IF($B25<=C$22,"n/a",(SUMPRODUCT(DCF!$D$23:$H$23/(1+$B25)^DCF!$D$25:$H$25)+DCF!$H$20*(1+C$22)*DCF!$B$35/($B25-C$22)/(1+$B25)^DCF!$B$38-DCF!$B$13)/DCF!$B$15) -> 206.26788 | D25: =IF($B25<=D$22,"n/a",(SUMPRODUCT(DCF!$D$23:$H$23/(1+$B25)^DCF!$D$25:$H$25)+DCF!$H$20*(1+D$22)*DCF!$B$35/($B25-D$22)/(1+$B25)^DCF!$B$38-DCF!$B$13)/DCF!$B$15) -> 225.65344 | E25: =IF($B25<=E$22,"n/a",(SUMPRODUCT(DCF!$D$23:$H$23/(1+$B25)^DCF!$D$25:$H$25)+DCF!$H$20*(1+E$22)*DCF!$B$35/($B25-E$22)/(1+$B25)^DCF!$B$38-DCF!$B$13)/DCF!$B$15) -> 248.87212 | F25: =IF($B25<=F$22,"n/a",(SUMPRODUCT(DCF!$D$23:$H$23/(1+$B25)^DCF!$D$25:$H$25)+DCF!$H$20*(1+F$22)*DCF!$B$35/($B25-F$22)/(1+$B25)^DCF!$B$38-DCF!$B$13)/DCF!$B$15) -> 277.18553 | G25: =IF($B25<=G$22,"n/a",(SUMPRODUCT(DCF!$D$23:$H$23/(1+$B25)^DCF!$D$25:$H$25)+DCF!$H$20*(1+G$22)*DCF!$B$35/($B25-G$22)/(1+$B25)^DCF!$B$38-DCF!$B$13)/DCF!$B$15) -> 312.47719
B26: =DCF!$B$7+(1)*$B$43 -> 0.080573866 | C26: =IF($B26<=C$22,"n/a",(SUMPRODUCT(DCF!$D$23:$H$23/(1+$B26)^DCF!$D$25:$H$25)+DCF!$H$20*(1+C$22)*DCF!$B$35/($B26-C$22)/(1+$B26)^DCF!$B$38-DCF!$B$13)/DCF!$B$15) -> 186.98797 | D26: =IF($B26<=D$22,"n/a",(SUMPRODUCT(DCF!$D$23:$H$23/(1+$B26)^DCF!$D$25:$H$25)+DCF!$H$20*(1+D$22)*DCF!$B$35/($B26-D$22)/(1+$B26)^DCF!$B$38-DCF!$B$13)/DCF!$B$15) -> 203.20742 | E26: =IF($B26<=E$22,"n/a",(SUMPRODUCT(DCF!$D$23:$H$23/(1+$B26)^DCF!$D$25:$H$25)+DCF!$H$20*(1+E$22)*DCF!$B$35/($B26-E$22)/(1+$B26)^DCF!$B$38-DCF!$B$13)/DCF!$B$15) -> 222.34542 | F26: =IF($B26<=F$22,"n/a",(SUMPRODUCT(DCF!$D$23:$H$23/(1+$B26)^DCF!$D$25:$H$25)+DCF!$H$20*(1+F$22)*DCF!$B$35/($B26-F$22)/(1+$B26)^DCF!$B$38-DCF!$B$13)/DCF!$B$15) -> 245.26759 | G26: =IF($B26<=G$22,"n/a",(SUMPRODUCT(DCF!$D$23:$H$23/(1+$B26)^DCF!$D$25:$H$25)+DCF!$H$20*(1+G$22)*DCF!$B$35/($B26-G$22)/(1+$B26)^DCF!$B$38-DCF!$B$13)/DCF!$B$15) -> 273.21942
B27: =DCF!$B$7+(2)*$B$43 -> 0.085573866 | C27: =IF($B27<=C$22,"n/a",(SUMPRODUCT(DCF!$D$23:$H$23/(1+$B27)^DCF!$D$25:$H$25)+DCF!$H$20*(1+C$22)*DCF!$B$35/($B27-C$22)/(1+$B27)^DCF!$B$38-DCF!$B$13)/DCF!$B$15) -> 170.4415 | D27: =IF($B27<=D$22,"n/a",(SUMPRODUCT(DCF!$D$23:$H$23/(1+$B27)^DCF!$D$25:$H$25)+DCF!$H$20*(1+D$22)*DCF!$B$35/($B27-D$22)/(1+$B27)^DCF!$B$38-DCF!$B$13)/DCF!$B$15) -> 184.18577 | E27: =IF($B27<=E$22,"n/a",(SUMPRODUCT(DCF!$D$23:$H$23/(1+$B27)^DCF!$D$25:$H$25)+DCF!$H$20*(1+E$22)*DCF!$B$35/($B27-E$22)/(1+$B27)^DCF!$B$38-DCF!$B$13)/DCF!$B$15) -> 200.19905 | F27: =IF($B27<=F$22,"n/a",(SUMPRODUCT(DCF!$D$23:$H$23/(1+$B27)^DCF!$D$25:$H$25)+DCF!$H$20*(1+F$22)*DCF!$B$35/($B27-F$22)/(1+$B27)^DCF!$B$38-DCF!$B$13)/DCF!$B$15) -> 219.09376 | G27: =IF($B27<=G$22,"n/a",(SUMPRODUCT(DCF!$D$23:$H$23/(1+$B27)^DCF!$D$25:$H$25)+DCF!$H$20*(1+G$22)*DCF!$B$35/($B27-G$22)/(1+$B27)^DCF!$B$38-DCF!$B$13)/DCF!$B$15) -> 241.72454
A29: BLENDED TARGET PRICE ($) - WACC vs TERMINAL GROWTH (comps held constant)
A30: WACC (rows) \ terminal growth (columns) | C30: =DCF!$B$8+(-2)*$B$44 -> 0.015 | D30: =DCF!$B$8+(-1)*$B$44 -> 0.02 | E30: =DCF!$B$8+(0)*$B$44 -> 0.025 | F30: =DCF!$B$8+(1)*$B$44 -> 0.03 | G30: =DCF!$B$8+(2)*$B$44 -> 0.035
B31: =DCF!$B$7+(-2)*$B$43 -> 0.065573866 | C31: =IF($B31<=C$30,"n/a",$B$7*(SUMPRODUCT(DCF!$D$23:$H$23/(1+$B31)^DCF!$D$25:$H$25)+DCF!$H$20*(1+C$30)*DCF!$B$35/($B31-C$30)/(1+$B31)^DCF!$B$38-DCF!$B$13)/DCF!$B$15+$B$8*$B$6) -> 253.017 | D31: =IF($B31<=D$30,"n/a",$B$7*(SUMPRODUCT(DCF!$D$23:$H$23/(1+$B31)^DCF!$D$25:$H$25)+DCF!$H$20*(1+D$30)*DCF!$B$35/($B31-D$30)/(1+$B31)^DCF!$B$38-DCF!$B$13)/DCF!$B$15+$B$8*$B$6) -> 270.45053 | E31: =IF($B31<=E$30,"n/a",$B$7*(SUMPRODUCT(DCF!$D$23:$H$23/(1+$B31)^DCF!$D$25:$H$25)+DCF!$H$20*(1+E$30)*DCF!$B$35/($B31-E$30)/(1+$B31)^DCF!$B$38-DCF!$B$13)/DCF!$B$15+$B$8*$B$6) -> 292.18081 | F31: =IF($B31<=F$30,"n/a",$B$7*(SUMPRODUCT(DCF!$D$23:$H$23/(1+$B31)^DCF!$D$25:$H$25)+DCF!$H$20*(1+F$30)*DCF!$B$35/($B31-F$30)/(1+$B31)^DCF!$B$38-DCF!$B$13)/DCF!$B$15+$B$8*$B$6) -> 320.01958 | G31: =IF($B31<=G$30,"n/a",$B$7*(SUMPRODUCT(DCF!$D$23:$H$23/(1+$B31)^DCF!$D$25:$H$25)+DCF!$H$20*(1+G$30)*DCF!$B$35/($B31-G$30)/(1+$B31)^DCF!$B$38-DCF!$B$13)/DCF!$B$15+$B$8*$B$6) -> 356.96377
B32: =DCF!$B$7+(-1)*$B$43 -> 0.070573866 | C32: =IF($B32<=C$30,"n/a",$B$7*(SUMPRODUCT(DCF!$D$23:$H$23/(1+$B32)^DCF!$D$25:$H$25)+DCF!$H$20*(1+C$30)*DCF!$B$35/($B32-C$30)/(1+$B32)^DCF!$B$38-DCF!$B$13)/DCF!$B$15+$B$8*$B$6) -> 236.66574 | D32: =IF($B32<=D$30,"n/a",$B$7*(SUMPRODUCT(DCF!$D$23:$H$23/(1+$B32)^DCF!$D$25:$H$25)+DCF!$H$20*(1+D$30)*DCF!$B$35/($B32-D$30)/(1+$B32)^DCF!$B$38-DCF!$B$13)/DCF!$B$15+$B$8*$B$6) -> 250.778 | E32: =IF($B32<=E$30,"n/a",$B$7*(SUMPRODUCT(DCF!$D$23:$H$23/(1+$B32)^DCF!$D$25:$H$25)+DCF!$H$20*(1+E$30)*DCF!$B$35/($B32-E$30)/(1+$B32)^DCF!$B$38-DCF!$B$13)/DCF!$B$15+$B$8*$B$6) -> 267.98684 | F32: =IF($B32<=F$30,"n/a",$B$7*(SUMPRODUCT(DCF!$D$23:$H$23/(1+$B32)^DCF!$D$25:$H$25)+DCF!$H$20*(1+F$30)*DCF!$B$35/($B32-F$30)/(1+$B32)^DCF!$B$38-DCF!$B$13)/DCF!$B$15+$B$8*$B$6) -> 289.43703 | G32: =IF($B32<=G$30,"n/a",$B$7*(SUMPRODUCT(DCF!$D$23:$H$23/(1+$B32)^DCF!$D$25:$H$25)+DCF!$H$20*(1+G$30)*DCF!$B$35/($B32-G$30)/(1+$B32)^DCF!$B$38-DCF!$B$13)/DCF!$B$15+$B$8*$B$6) -> 316.91698
B33: =DCF!$B$7+(0)*$B$43 -> 0.075573866 | C33: =IF($B33<=C$30,"n/a",$B$7*(SUMPRODUCT(DCF!$D$23:$H$23/(1+$B33)^DCF!$D$25:$H$25)+DCF!$H$20*(1+C$30)*DCF!$B$35/($B33-C$30)/(1+$B33)^DCF!$B$38-DCF!$B$13)/DCF!$B$15+$B$8*$B$6) -> 223.01503 | D33: =IF($B33<=D$30,"n/a",$B$7*(SUMPRODUCT(DCF!$D$23:$H$23/(1+$B33)^DCF!$D$25:$H$25)+DCF!$H$20*(1+D$30)*DCF!$B$35/($B33-D$30)/(1+$B33)^DCF!$B$38-DCF!$B$13)/DCF!$B$15+$B$8*$B$6) -> 234.64636 | E33: =IF($B33<=E$30,"n/a",$B$7*(SUMPRODUCT(DCF!$D$23:$H$23/(1+$B33)^DCF!$D$25:$H$25)+DCF!$H$20*(1+E$30)*DCF!$B$35/($B33-E$30)/(1+$B33)^DCF!$B$38-DCF!$B$13)/DCF!$B$15+$B$8*$B$6) -> 248.57757 | F33: =IF($B33<=F$30,"n/a",$B$7*(SUMPRODUCT(DCF!$D$23:$H$23/(1+$B33)^DCF!$D$25:$H$25)+DCF!$H$20*(1+F$30)*DCF!$B$35/($B33-F$30)/(1+$B33)^DCF!$B$38-DCF!$B$13)/DCF!$B$15+$B$8*$B$6) -> 265.56562 | G33: =IF($B33<=G$30,"n/a",$B$7*(SUMPRODUCT(DCF!$D$23:$H$23/(1+$B33)^DCF!$D$25:$H$25)+DCF!$H$20*(1+G$30)*DCF!$B$35/($B33-G$30)/(1+$B33)^DCF!$B$38-DCF!$B$13)/DCF!$B$15+$B$8*$B$6) -> 286.74061
B34: =DCF!$B$7+(1)*$B$43 -> 0.080573866 | C34: =IF($B34<=C$30,"n/a",$B$7*(SUMPRODUCT(DCF!$D$23:$H$23/(1+$B34)^DCF!$D$25:$H$25)+DCF!$H$20*(1+C$30)*DCF!$B$35/($B34-C$30)/(1+$B34)^DCF!$B$38-DCF!$B$13)/DCF!$B$15+$B$8*$B$6) -> 211.44708 | D34: =IF($B34<=D$30,"n/a",$B$7*(SUMPRODUCT(DCF!$D$23:$H$23/(1+$B34)^DCF!$D$25:$H$25)+DCF!$H$20*(1+D$30)*DCF!$B$35/($B34-D$30)/(1+$B34)^DCF!$B$38-DCF!$B$13)/DCF!$B$15+$B$8*$B$6) -> 221.17875 | E34: =IF($B34<=E$30,"n/a",$B$7*(SUMPRODUCT(DCF!$D$23:$H$23/(1+$B34)^DCF!$D$25:$H$25)+DCF!$H$20*(1+E$30)*DCF!$B$35/($B34-E$30)/(1+$B34)^DCF!$B$38-DCF!$B$13)/DCF!$B$15+$B$8*$B$6) -> 232.66155 | F34: =IF($B34<=F$30,"n/a",$B$7*(SUMPRODUCT(DCF!$D$23:$H$23/(1+$B34)^DCF!$D$25:$H$25)+DCF!$H$20*(1+F$30)*DCF!$B$35/($B34-F$30)/(1+$B34)^DCF!$B$38-DCF!$B$13)/DCF!$B$15+$B$8*$B$6) -> 246.41485 | G34: =IF($B34<=G$30,"n/a",$B$7*(SUMPRODUCT(DCF!$D$23:$H$23/(1+$B34)^DCF!$D$25:$H$25)+DCF!$H$20*(1+G$30)*DCF!$B$35/($B34-G$30)/(1+$B34)^DCF!$B$38-DCF!$B$13)/DCF!$B$15+$B$8*$B$6) -> 263.18595
B35: =DCF!$B$7+(2)*$B$43 -> 0.085573866 | C35: =IF($B35<=C$30,"n/a",$B$7*(SUMPRODUCT(DCF!$D$23:$H$23/(1+$B35)^DCF!$D$25:$H$25)+DCF!$H$20*(1+C$30)*DCF!$B$35/($B35-C$30)/(1+$B35)^DCF!$B$38-DCF!$B$13)/DCF!$B$15+$B$8*$B$6) -> 201.5192 | D35: =IF($B35<=D$30,"n/a",$B$7*(SUMPRODUCT(DCF!$D$23:$H$23/(1+$B35)^DCF!$D$25:$H$25)+DCF!$H$20*(1+D$30)*DCF!$B$35/($B35-D$30)/(1+$B35)^DCF!$B$38-DCF!$B$13)/DCF!$B$15+$B$8*$B$6) -> 209.76576 | E35: =IF($B35<=E$30,"n/a",$B$7*(SUMPRODUCT(DCF!$D$23:$H$23/(1+$B35)^DCF!$D$25:$H$25)+DCF!$H$20*(1+E$30)*DCF!$B$35/($B35-E$30)/(1+$B35)^DCF!$B$38-DCF!$B$13)/DCF!$B$15+$B$8*$B$6) -> 219.37373 | F35: =IF($B35<=F$30,"n/a",$B$7*(SUMPRODUCT(DCF!$D$23:$H$23/(1+$B35)^DCF!$D$25:$H$25)+DCF!$H$20*(1+F$30)*DCF!$B$35/($B35-F$30)/(1+$B35)^DCF!$B$38-DCF!$B$13)/DCF!$B$15+$B$8*$B$6) -> 230.71056 | G35: =IF($B35<=G$30,"n/a",$B$7*(SUMPRODUCT(DCF!$D$23:$H$23/(1+$B35)^DCF!$D$25:$H$25)+DCF!$H$20*(1+G$30)*DCF!$B$35/($B35-G$30)/(1+$B35)^DCF!$B$38-DCF!$B$13)/DCF!$B$15+$B$8*$B$6) -> 244.28902
A42: SENSITIVITY SETTINGS & CHECKS
A43: WACC step | B43: 0.005 | C43: % | H43: Base WACC +/- 2 steps (about 6.5-8.5%): covers the beta sensitivities on WACC rows 54-64.
A44: Terminal growth step | B44: 0.005 | C44: % | H44: Base g +/- 2 steps (1.5%-3.5%).
A45: Check: DCF grid centre - DCF value (should be 0) | B45: =E25-B5 -> 0 | C45: $
A46: Check: blended grid centre - target (should be 0) | B46: =E33-B9 -> 0 | C46: $
A48: Rating band: 'Buy' at or above total return of | B48: 0.1 | C48: % | H48: REVISED 26-Sep (round 4): exact bands. Buy >= +10%; Hold > -10% and < +10%; Sell <= -10% (12-month total return including dividends). Replaces "Buy above +10 to 15%".
A50: Rating band: 'Sell' at or below total return of | B50: -0.1 | C50: %
A52: BETA / WACC CHECK - target under each beta estimate (primary = franchise-heavy bottom-up)
A53: Beta estimate | B53: WACC | C53: DCF $/sh | D53: Target $/sh | E53: Upside | F53: Total return | G53: Rating | H53: Note
A54: Primary: franchise-heavy bottom-up beta (mean) | B54: =WACC!C55 -> 0.075573866 | C54: =IF($B54<=DCF!$B$8,"n/a",(SUMPRODUCT(DCF!$D$23:$H$23/(1+$B54)^DCF!$D$25:$H$25)+DCF!$H$20*(1+DCF!$B$8)*DCF!$B$35/($B54-DCF!$B$8)/(1+$B54)^DCF!$B$38-DCF!$B$13)/DCF!$B$15) -> 248.87212 | D54: =C54*$B$7+$B$6*$B$8 -> 248.57757 | E54: =D54/$B$10-1 -> 0.048762 | F54: =E54+$B$12 -> 0.081333091 | G54: =IF(F54>=$B$48,"Buy",IF(F54<=$B$50,"Sell","Hold")) -> Hold | H54: Beta ~0.60; used in the target.
A55: Low: franchise-heavy median beta | B55: =WACC!C54 -> 0.07223959 | C55: =IF($B55<=DCF!$B$8,"n/a",(SUMPRODUCT(DCF!$D$23:$H$23/(1+$B55)^DCF!$D$25:$H$25)+DCF!$H$20*(1+DCF!$B$8)*DCF!$B$35/($B55-DCF!$B$8)/(1+$B55)^DCF!$B$38-DCF!$B$13)/DCF!$B$15) -> 269.68325 | D55: =C55*$B$7+$B$6*$B$8 -> 261.06425 | E55: =D55/$B$10-1 -> 0.10144397 | F55: =E55+$B$12 -> 0.13401506 | G55: =IF(F55>=$B$48,"Buy",IF(F55<=$B$50,"Sell","Hold")) -> Buy | H55: Beta ~0.52.
A56: Conservative blend (75 / 25) | B56: =WACC!C56 -> 0.077539442 | C56: =IF($B56<=DCF!$B$8,"n/a",(SUMPRODUCT(DCF!$D$23:$H$23/(1+$B56)^DCF!$D$25:$H$25)+DCF!$H$20*(1+DCF!$B$8)*DCF!$B$35/($B56-DCF!$B$8)/(1+$B56)^DCF!$B$38-DCF!$B$13)/DCF!$B$15) -> 237.84164 | D56: =C56*$B$7+$B$6*$B$8 -> 241.95928 | E56: =D56/$B$10-1 -> 0.020839103 | F56: =E56+$B$12 -> 0.053410194 | G56: =IF(F56>=$B$48,"Buy",IF(F56<=$B$50,"Sell","Hold")) -> Hold | H56: Beta ~0.65.
A57: High: all five peers, bottom-up mean | B57: =WACC!C57 -> 0.083436171 | C57: =IF($B57<=DCF!$B$8,"n/a",(SUMPRODUCT(DCF!$D$23:$H$23/(1+$B57)^DCF!$D$25:$H$25)+DCF!$H$20*(1+DCF!$B$8)*DCF!$B$35/($B57-DCF!$B$8)/(1+$B57)^DCF!$B$38-DCF!$B$13)/DCF!$B$15) -> 209.20357 | D57: =C57*$B$7+$B$6*$B$8 -> 224.77644 | E57: =D57/$B$10-1 -> -0.051656235 | F57: =E57+$B$12 -> -0.019085144 | G57: =IF(F57>=$B$48,"Buy",IF(F57<=$B$50,"Sell","Hold")) -> Hold | H57: Beta ~0.80.
A58: Earlier base: average of three methods | B58: =WACC!C64 -> 0.081022969 | C58: =IF($B58<=DCF!$B$8,"n/a",(SUMPRODUCT(DCF!$D$23:$H$23/(1+$B58)^DCF!$D$25:$H$25)+DCF!$H$20*(1+DCF!$B$8)*DCF!$B$35/($B58-DCF!$B$8)/(1+$B58)^DCF!$B$38-DCF!$B$13)/DCF!$B$15) -> 220.19458 | D58: =C58*$B$7+$B$6*$B$8 -> 231.37105 | E58: =D58/$B$10-1 -> -0.023833228 | F58: =E58+$B$12 -> 0.0087378631 | G58: =IF(F58>=$B$48,"Buy",IF(F58<=$B$50,"Sell","Hold")) -> Hold | H58: Round-2 base (8.03%); replaced.
A59: Check: primary row - target (should be 0) | B59: =D54-B9 -> 0
A61: CONSENSUS CROSS-CHECK (added after feedback)
A62: Implied consensus NTM EPS (source price / consensus forward P/E) | B62: =Peers!C24/Peers!H24 -> 13.31614 | H62: Stock Analysis forward P/E is built on consensus EPS: $240.09 / 18.03x.
A63: Model NTM EPS (calendarised, adjusted) | B63: =Comps!C23 -> 13.347176 | H63: Comps tab.
A64: Model vs consensus NTM EPS | B64: =B63/B62-1 -> 0.0023307301 | H64: Our earnings path is in line with the Street; the valuation gap comes from the multiple and discount rate, not from EPS.
A65: Street mean 12-month target price | B65: 311.55 | H65: Stock Analysis MCD overview, 35 analysts, consensus 'Buy', accessed 25-Sep-2026. Several targets were cut after Investor Day (e.g. JPMorgan $260, Baird $250).
A66: Our target vs Street mean | B66: =B9/B65-1 -> -0.20212624
A68: SCENARIOS, REVERSE DCF AND SENSITIVITIES (numbers used in the report)
A69: Item | B69: Bear | C69: Base | D69: Bull | H69: Note
A70: DCF value in the original scenario runs (WACC 8.04%) | B70: 189 | C70: 223.34 | D70: 241 | H70: Original deck, Figure 14. Scenario forecasts were run outside this workbook.
A71: Enterprise value relative to base (from those runs) | B71: =(B70*DCF!$B$15+DCF!$B$13)/($C$70*DCF!$B$15+DCF!$B$13) -> 0.87564851 | C71: =(C70*DCF!$B$15+DCF!$B$13)/($C$70*DCF!$B$15+DCF!$B$13) -> 1 | D71: =(D70*DCF!$B$15+DCF!$B$13)/($C$70*DCF!$B$15+DCF!$B$13) -> 1.0639501 | H71: EV = value x diluted shares + fair-value net debt.
A72: DCF value at the current WACC (EV ratio x current EV) | B72: =(B71*DCF!$B$45-DCF!$B$13)/DCF!$B$15 -> 211.35716 | C72: =(C71*DCF!$B$45-DCF!$B$13)/DCF!$B$15 -> 248.87212 | D72: =(D71*DCF!$B$45-DCF!$B$13)/DCF!$B$15 -> 268.1649 | H72: Approximation: keeps each scenario's EV ratio to base; exact for the base.
A73: Blended target in the original runs | B73: 227 | C73: 251.08 | D73: 263 | H73: Original deck, Figure 14.
A74: Comps value relative to base (implied by those runs) | B74: =((B73-0.6*B70)/0.4)/(($C$73-0.6*$C$70)/0.4) -> 0.97030988 | C74: =((C73-0.6*C70)/0.4)/(($C$73-0.6*$C$70)/0.4) -> 1 | D74: =((D73-0.6*D70)/0.4)/(($C$73-0.6*$C$70)/0.4) -> 1.0113089 | H74: Comps move with NTM EPS in each scenario; 0.6 / 0.4 = the weights used in those runs.
A75: Comps value (franchise-heavy) | B75: =B74*Comps!$D$31 -> 240.76857 | C75: =C74*Comps!$D$31 -> 248.13575 | D75: =D74*Comps!$D$31 -> 250.94189
A76: Blended target | B76: =B72*$B$7+B75*$B$8 -> 223.12172 | C76: =C72*$B$7+C75*$B$8 -> 248.57757 | D76: =D72*$B$7+D75*$B$8 -> 261.27569
A77: vs current price | B77: =B76/$B$10-1 -> -0.058637569 | C77: =C76/$B$10-1 -> 0.048762 | D77: =D76/$B$10-1 -> 0.10233607
A78: Probability | B78: 0.25 | C78: 0.5 | D78: 0.25
A79: Probability-weighted target | B79: =SUMPRODUCT(B76:D76,B78:D78) -> 245.38814
A81: Reverse DCF: price-implied perpetual growth (WACC held) | B81: =((($B$10*DCF!$B$15+DCF!$B$13-DCF!$B$43)*(1+DCF!$B$7)^DCF!$B$38/(DCF!$H$20*DCF!$B$35))*DCF!$B$7-1)/(1+(($B$10*DCF!$B$15+DCF!$B$13-DCF!$B$43)*(1+DCF!$B$7)^DCF!$B$38/(DCF!$H$20*DCF!$B$35))) -> 0.022565544 | H81: Closed form: solves the terminal value so the DCF equals the price.
A82: Reverse DCF: price-implied WACC (g held) | B82: 0.077692 | H82: Solved by iteration outside Excel on a replica of Forecast / DCF (goal seek); re-run if inputs change.
A83: Reverse DCF: price-implied change in comps every year FY26-30 | B83: -0.00707 | H83: Same replica; negative = the price assumes weaker comps than our forecast.
A84: Sensitivity: 2028-30 operating margin -1pp: DCF value | B84: 242.90516 | H84: Same replica; margin cut carried into the terminal year.
A85: Sensitivity: 2028-30 operating margin -1pp: blended target | B85: =B84*$B$7+$B$6*$B$8 -> 244.9974
A86: Sensitivity: WACC -0.5pp / +0.5pp: blended target | B86: =E32 -> 267.98684 | C86: =E34 -> 232.66155
A87: Sensitivity: WACC -0.5pp / +0.5pp: DCF value | B87: =E24 -> 281.2209 | C87: =E26 -> 222.34542
A89: COMPS WEIGHTING CHECK (round 4): target if comps used only one multiple | D89: Total return
A90: Target with comps on forward P/E only | B90: =$B$5*$B$7+Comps!D29*$B$8 -> 238.55303 | C90: =B90/$B$10-1+$B$12 -> 0.03903902 | H90: Franchise-heavy median forward P/E x NTM EPS.
A91: Target with comps on EV/EBITDA only | B91: =$B$5*$B$7+Comps!D30*$B$8 -> 258.60211 | C91: =B91/$B$10-1+$B$12 -> 0.12362716 | H91: Franchise-heavy median LTM EV/EBITDA x LTM EBITDA.
A92: Target with 50/50 (base) | B92: =B9 -> 248.57757 | C92: =B92/$B$10-1+$B$12 -> 0.081333091 | H92: See Comps P31 for why the two get equal weight.

Sheet DCF
A1: Discounted cash flow - intrinsic value per share
A2: Unlevered FCF from Forecast. Stub period from the latest balance sheet (30-Jun-2026), mid-year convention, normalised terminal year. Orange = changed after the review.
A4: INPUTS
A5: Valuation date | B5: =Market_WACC!B7 -> 46289 | J5: Price date
A6: Balance sheet date (latest 10-Q) | B6: =DATE(2026,6,30) -> 46203 | J6: NEW: net debt from the Q2-2026 10-Q instead of FY25 year-end (multiples guide Key Rule #15: update the bridge to the latest interim balance sheet).
A7: WACC | B7: =WACC!B39 -> 0.075573866 | C7: % | J7: WACC tab B39: primary bottom-up beta from franchise-heavy peers (revised 26-Sep).
A8: Terminal growth rate | B8: 0.025 | C8: % | J8: REVISED from 3.0%: guide says 1-3% for developed markets, "perhaps in line with inflation" and below GDP growth (DCF guide Key Rule #6). 3.0% sat at the ceiling; 2.5% is the midpoint of the plausible range.
A9: Mid-year convention (1 = on, 0 = year-end) | B9: 1 | J9: NEW: cash arrives through the year, so mid-year discounting is more accurate (DCF guide Key Rule #11). Stub handled as the guide describes.
A10: Cash & equivalents (30-Jun-2026) | B10: 822 | C10: $mm | J10: MCD 10-Q Q2-2026 balance sheet.
A11: Long-term debt, carrying (30-Jun-2026) | B11: 39863 | C11: $mm | J11: MCD 10-Q Q2-2026 balance sheet.
A12: Debt at fair value (30-Jun-2026) | B12: 38300 | C12: $mm | J12: MCD 10-Q Q2-2026 fair value note: $38.3bn (quoted prices, Level 2).
A13: Net debt used in bridge (fair-value debt - cash) | B13: =B12-B10 -> 37478 | C13: $mm | J13: Market value of debt per multiples guide Key Rule #10. Book-value alternative: $39,041m (-$2.2/share).
A14: Memo: operating lease liabilities (not deducted) | B14: =690+14039 -> 14729 | C14: $mm | J14: 10-Q: current $690m + long-term $14,039m. Not deducted because rent is already inside FCF (no double counting).
A15: Diluted shares | B15: =WACC!B11 -> 709.64 | C15: mm | J15: WACC tab
A16: Current share price | B16: =Market_WACC!B6 -> 237.02 | C16: $ | J16: Market_WACC
A18: Free cash flow | B18: Unit | D18: FY2026E | E18: FY2027E | F18: FY2028E | G18: FY2029E | H18: FY2030E | I18: Terminal (FY31 norm.) | J18: Note
A19: Fiscal year end | D19: =DATE(2026,12,31) -> 46387 | E19: =DATE(2027,12,31) -> 46752 | F19: =DATE(2028,12,31) -> 47118 | G19: =DATE(2029,12,31) -> 47483 | H19: =DATE(2030,12,31) -> 47848
A20: Revenue | C20: $mm | D20: =Forecast!D21 -> 28363.675 | E20: =Forecast!E21 -> 28221.857 | F20: =Forecast!F21 -> 28165.413 | G20: =Forecast!G21 -> 29348.36 | H20: =Forecast!H21 -> 30580.991 | I20: =H20*(1+B8) -> 31345.516
A21: Unlevered free cash flow | C21: $mm | D21: =Forecast!D43 -> 8445.3079 | E21: =Forecast!E43 -> 9456.8762 | F21: =Forecast!F43 -> 10004.618 | G21: =Forecast!G43 -> 10798.629 | H21: =Forecast!H43 -> 11516.337 | I21: =I20*B35 -> 11617.393 | J21: Forecast row 43.
A22: Share of year after balance-sheet date | C22: % | D22: =MAX(0,MIN(1,(D19-$B$6)/365)) -> 0.50410959 | E22: =MAX(0,MIN(1,(E19-$B$6)/365)) -> 1 | F22: =MAX(0,MIN(1,(F19-$B$6)/365)) -> 1 | G22: =MAX(0,MIN(1,(G19-$B$6)/365)) -> 1 | H22: =MAX(0,MIN(1,(H19-$B$6)/365)) -> 1 | J22: FY26: only H2 cash flow is counted, because H1 cash is already reflected in the 30-Jun net debt (DCF guide Key Rule #11, stub periods).
A23: FCF counted | C23: $mm | D23: =D21*D22 -> 4257.3607 | E23: =E21*E22 -> 9456.8762 | F23: =F21*F22 -> 10004.618 | G23: =G21*G22 -> 10798.629 | H23: =H21*H22 -> 11516.337
A24: Cash-flow timing date | D24: =IF($B$9=1,D19-(D19-MAX($B$6,D19-365))/2,D19) -> 46295 | E24: =IF($B$9=1,E19-(E19-MAX($B$6,E19-365))/2,E19) -> 46569.5 | F24: =IF($B$9=1,F19-(F19-MAX($B$6,F19-365))/2,F19) -> 46935.5 | G24: =IF($B$9=1,G19-(G19-MAX($B$6,G19-365))/2,G19) -> 47300.5 | H24: =IF($B$9=1,H19-(H19-MAX($B$6,H19-365))/2,H19) -> 47665.5 | J24: Mid-year: midpoint of the period counted (30-Sep for the FY26 stub, ~1-Jul after). Year-end if the switch is 0.
A25: Discount period (years from valuation date) | C25: yrs | D25: =MAX(0,(D24-$B$5)/365) -> 0.016438356 | E25: =MAX(0,(E24-$B$5)/365) -> 0.76849315 | F25: =MAX(0,(F24-$B$5)/365) -> 1.7712329 | G25: =MAX(0,(G24-$B$5)/365) -> 2.7712329 | H25: =MAX(0,(H24-$B$5)/365) -> 3.7712329
A26: Discount factor | D26: =1/(1+$B$7)^D25 -> 0.99880311 | E26: =1/(1+$B$7)^E25 -> 0.94555042 | F26: =1/(1+$B$7)^F25 -> 0.87893704 | G26: =1/(1+$B$7)^G25 -> 0.81717961 | H26: =1/(1+$B$7)^H25 -> 0.7597615
A27: PV of FCF | C27: $mm | D27: =D23*D26 -> 4252.2651 | E27: =E23*E26 -> 8941.9533 | F27: =F23*F26 -> 8793.4291 | G27: =G23*G26 -> 8824.4194 | H27: =H23*H26 -> 8749.6696
A29: NORMALISED TERMINAL YEAR & TERMINAL VALUE
A30: Operating margin held at FY2030 level | B30: =Forecast!H10 -> 0.53 | C30: % | J30: Margin expansion stops at the 2030 target.
A31: Tax rate | B31: =Forecast!H14 -> 0.22 | C31: %
A32: D&A % of revenue | B32: =Forecast!H11 -> 0.086 | C32: %
A33: Capex % of revenue (normalised) | B33: =AVERAGE(Forecast!E45:H45) -> 0.11877623 | C33: % | J33: NEW: FY27-30 average instead of the falling FY30 ratio. Flat $3.45bn capex makes FY30 capex % unusually low, and NEXT partnering runs to 2036 (DCF guide Key Rule #11, normalised terminal year).
A34: Working capital & other % of revenue | B34: =Forecast!H13 -> -0.01 | C34: %
A35: Normalised UFCF margin | B35: =B30*(1-B31)+B32-B33+B34 -> 0.37062377 | C35: % | J35: Terminal-year UFCF = FY31 revenue x this margin.
A36: Terminal-year UFCF vs FY2030 UFCF | B36: =I21/H21-1 -> 0.0087750208 | C36: % | J36: Growth into the terminal year after normalising capex.
A37: Terminal value at end-FY2030 | B37: =IF(B7>B8,I21/(B7-B8),"") -> 229711.39 | C37: $mm | J37: Perpetuity growth: terminal-year UFCF / (WACC - g).
A38: Terminal-value discount period | B38: =(H19-B5)/365-IF(B9=1,0.5,0) -> 3.7712329 | C38: yrs | J38: Half a year earlier under the mid-year convention with the perpetuity method (DCF guide Key Rule #11).
A39: PV of terminal value | B39: =IF(B37="","",B37/(1+B7)^B38) -> 174525.87 | C39: $mm
A40: Implied exit EV/EBITDA (TV / FY2030E EBITDA) | B40: =IF(B37="","",B37/Forecast!H25) -> 12.194114 | C40: x | J40: Cross-check vs lease-adjusted peer median and MCD today (checks below).
A42: ENTERPRISE VALUE TO VALUE PER SHARE
A43: Sum of PV of FCF (H2-FY26 to FY30) | B43: =SUM(D27:H27) -> 39561.736 | C43: $mm
A44: PV of terminal value | B44: =B39 -> 174525.87 | C44: $mm
A45: Enterprise value | B45: =B43+B44 -> 214087.61 | C45: $mm
A46: Terminal value % of EV | B46: =B44/B45 -> 0.81520773 | C46: %
A47: Less: net debt (fair value, 30-Jun-2026) | B47: =-B13 -> -37478 | C47: $mm
A48: Equity value | B48: =B45+B47 -> 176609.61 | C48: $mm
A49: Diluted shares | B49: =B15 -> 709.64 | C49: mm
A50: Intrinsic value per share (DCF) | B50: =B48/B49 -> 248.87212 | C50: $
A51: Upside / (downside) vs current price | B51: =B50/B16-1 -> 0.050004719 | C51: %
A53: GUIDE CHECKS (DCF guide Key Rules #4 and #6)
A54: Check | B54: Value | D54: Test | I54: Result | J54: What it means
A55: Capex % > D&A % in FY2030 | B55: =Forecast!H45-Forecast!H11 -> 0.026815178 | D55: capex% - D&A% > 0 | I55: =IF(B55>0,"PASS","REVIEW") -> PASS | J55: A growing company must reinvest more than it depreciates.
A56: Operating-margin change in final forecast year | B56: =Forecast!H23-Forecast!G23 -> 0.005 | D56: <= 0.5pp | I56: =IF(B56<=0.0051,"PASS","REVIEW") -> PASS | J56: Margins should have stabilised by the end of the forecast.
A57: FY2030 UFCF growth | B57: =Forecast!H44 -> 0.066462908 | D57: context only | I57: ="see row 58" -> see row 58 | J57: Still above g because capex is flat in $; the normalised terminal year fixes this.
A58: Growth into terminal year (normalised) | B58: =B36 -> 0.0087750208 | D58: within 2pp of g | I58: =IF(ABS(B58-B8)<=0.02,"PASS","REVIEW") -> PASS | J58: The transition into the terminal period should not be abrupt.
A59: Terminal growth within 1-3% (developed markets) | B59: =B8 -> 0.025 | D59: 1% <= g <= 3% | I59: =IF(AND(B59>=0.01,B59<=0.03),"PASS","REVIEW") -> PASS | J59: No company can outgrow the economy forever.
A60: Terminal growth below risk-free rate | B60: =WACC!B6-B8 -> 0.0268 | D60: rf - g > 0 | I60: =IF(B60>0,"PASS","REVIEW") -> PASS | J60: Proxy for long-run nominal growth.
A61: Implied exit multiple vs lease-adjusted franchise-heavy peer median | B61: =B40-Comps!I14 -> -3.1565317 | D61: at or below peers | I61: =IF(B61<=0,"PASS","REVIEW") -> PASS | J61: REVISED (feedback): compared with the franchise-heavy median (primary comps set). Exit multiple should not exceed today's peer multiples as growth slows.
A62: Implied exit multiple vs MCD LTM EV/EBITDA today | B62: =B40-Comps!D37 -> -1.4530804 | D62: context only | I62: ="info" -> info | J62: Negative = terminal value assumes some multiple compression.

Sheet Forecast
A1: Five-year forecast (FY2026E-FY2030E)
A2: Blue on yellow = assumption (one per line). Black = formula. Green = link. Orange fill = changed after the review against the valuation guides (see Model_Review). $ millions unless stated.
A4: Line item | B4: Unit | C4: FY2025A | D4: FY2026E | E4: FY2027E | F4: FY2028E | G4: FY2029E | H4: FY2030E | I4: Source / rationale
A5: A. ASSUMPTIONS (one per line)
A6: Comparable sales growth | B6: % | D6: 0.02 | E6: 0.025 | F6: 0.03 | G6: 0.03 | H6: 0.03 | I6: H1-26 comps +2.5%, Q2 +1.3%, U.S. July slightly negative; IOM/IDL expected to accelerate in Q3 -> ~2% FY26. U.S. recovery "a 2027 story" (Q2 call); Investor Day share-gain targets with flat industry traffic -> 3% steady state.
A7: New-restaurant contribution to revenue growth | B7: % | D7: 0.015 | E7: 0.015 | F7: 0.013 | G7: 0.012 | H7: 0.012 | I7: Investor Day: new units add ~2.5% to systemwide sales 2026-27, easing to ~2% by 2030. Cut ~40% for revenue because most openings are IDL (royalty ~5% vs ~14-17% take in U.S./IOM).
A8: FX translation impact on revenue | B8: % | D8: 0.025 | E8: 0 | F8: 0 | G8: 0 | H8: 0 | I8: H1-26 revenue +6.4% reported vs +3% cc (Q2 release p.2). No FX assumed after FY26.
A9: Refranchising impact on revenue | B9: % | D9: -0.005 | E9: -0.045 | F9: -0.045 | G9: 0 | H9: 0 | I9: Investor Day: franchised mix ~95% -> ~98% by end-2028 (2,012 company units at 30-Jun-26, 10-Q). Swaps company sales for ~15% rent/royalty: lowers revenue, broadly neutral to operating income, lifts margin %.
A10: Operating margin (adjusted, before restructuring) | B10: % | D10: 0.47 | E10: 0.495 | F10: 0.515 | G10: 0.525 | H10: 0.53 | I10: REVISED: ramp smoothed so the final-year step is 0.5pp (was 0.7pp) - DCF guide Key Rule #4: margins should stabilise by the end of the forecast. FY25 adj. 46.9%; Investor Day target low-to-mid 50s by 2030; 53% = low end.
A11: D&A as % of revenue | B11: % | D11: 0.082 | E11: 0.084 | F11: 0.086 | G11: 0.086 | H11: 0.086 | I11: FY25 8.2%. H1-26 D&A $1,131m (10-Q cash flow) ~ 8.3% of H1 revenue. Drifts up as capex rises and refranchising shrinks revenue.
A12: Capital expenditures | B12: $mm | D12: 3800 | E12: 3450 | F12: 3450 | G12: 3450 | H12: 3450 | I12: FY26 guide $3.7-3.9bn (H1 actual $1,516m). Investor Day: ~$3.0bn baseline p.a. 2027-30 + $1.5-2.0bn cumulative NEXT capital partnering.
A13: Change in working capital & other operating items | B13: % rev | D13: -0.01 | E13: -0.01 | F13: -0.01 | G13: -0.01 | H13: -0.01 | I13: REVISED LABEL: stock-based compensation is NOT added back (DCF guide Key Rule #2 - SBC is a real cost); it stays expensed inside operating income. CFO - NI - D&A ran -3.3% / -3.4% / -0.8% of revenue FY23-25.
A14: Tax rate | B14: % | D14: 0.22 | E14: 0.22 | F14: 0.22 | G14: 0.22 | H14: 0.22 | I14: FY26 guidance 21-23% -> 22%. Applied to operating income with no interest tax shield (DCF guide Key Rule #4).
A15: Interest expense growth | B15: % | D15: 0.05 | E15: 0.04 | F15: 0.04 | G15: 0.03 | H15: 0.03 | I15: FY26 guide +4-6%. EPS only (DCF is unlevered).
A16: Diluted share count change (buybacks) | B16: % | D16: -0.008 | E16: -0.008 | F16: -0.008 | G16: -0.008 | H16: -0.008 | I16: EPS only. FY21-25 diluted shares -1.2% p.a.
A17: Restructuring & special charges (pre-tax, cash) | B17: $mm | D17: 250 | E17: 100 | F17: 0 | G17: 0 | H17: 0 | I17: NEW: charges recurred every year 2023-26 ($795m cumulative), so they are not "non-recurring" (DCF guide Key Rule #8) and must reduce cash flow. 10-Q Q2-26: ~$250m expected in 2026, programme completes during 2027.
A19: B. INCOME STATEMENT (adjusted basis, for EPS and multiples)
A20: Revenue growth | B20: % | C20: =Historical_5Y!G12 -> 0.037229938 | D20: =SUM(D6:D9) -> 0.055 | E20: =SUM(E6:E9) -> -0.005 | F20: =SUM(F6:F9) -> -0.002 | G20: =SUM(G6:G9) -> 0.042 | H20: =SUM(H6:H9) -> 0.042 | I20: Comps + new units + FX + refranchising (rows 6-9).
A21: Total revenues | B21: $mm | C21: =Historical_5Y!G9 -> 26885 | D21: =C21*(1+D20) -> 28363.675 | E21: =D21*(1+E20) -> 28221.857 | F21: =E21*(1+F20) -> 28165.413 | G21: =F21*(1+G20) -> 29348.36 | H21: =G21*(1+H20) -> 30580.991
A22: Operating income (adjusted) | B22: $mm | C22: =Historical_5Y!G16 -> 12621 | D22: =D21*D10 -> 13330.927 | E22: =E21*E10 -> 13969.819 | F22: =F21*F10 -> 14505.188 | G22: =G21*G10 -> 15407.889 | H22: =H21*H10 -> 16207.925 | I22: FY25A non-GAAP (excl. $229m restructuring).
A23: Operating margin (adjusted) | B23: % | C23: =C22/C21 -> 0.46944393 | D23: =D22/D21 -> 0.47 | E23: =E22/E21 -> 0.495 | F23: =F22/F21 -> 0.515 | G23: =G22/G21 -> 0.525 | H23: =H22/H21 -> 0.53
A24: Depreciation & amortization | B24: $mm | C24: =Historical_5Y!G22 -> 2199 | D24: =D21*D11 -> 2325.8214 | E24: =E21*E11 -> 2370.636 | F24: =F21*F11 -> 2422.2255 | G24: =G21*G11 -> 2523.959 | H24: =H21*H11 -> 2629.9653 | I24: Cash-flow-statement D&A (the all-inclusive figure - multiples guide Key Rule #4).
A25: EBITDA (adjusted) | B25: $mm | C25: =C22+C24 -> 14820 | D25: =D22+D24 -> 15656.749 | E25: =E22+E24 -> 16340.455 | F25: =F22+F24 -> 16927.413 | G25: =G22+G24 -> 17931.848 | H25: =H22+H24 -> 18837.891
A26: Interest expense | B26: $mm | C26: =Reference_Data!E22 -> 1582 | D26: =C26*(1+D15) -> 1661.1 | E26: =D26*(1+E15) -> 1727.544 | F26: =E26*(1+F15) -> 1796.6458 | G26: =F26*(1+G15) -> 1850.5451 | H26: =G26*(1+H15) -> 1906.0615 | I26: FY25A 10-K p.39.
A27: Pre-tax income (adjusted) | B27: $mm | D27: =D22-D26 -> 11669.827 | E27: =E22-E26 -> 12242.275 | F27: =F22-F26 -> 12708.542 | G27: =G22-G26 -> 13557.344 | H27: =H22-H26 -> 14301.864
A28: Income taxes | B28: $mm | D28: =D27*D14 -> 2567.362 | E28: =E27*E14 -> 2693.3005 | F28: =F27*F14 -> 2795.8792 | G28: =G27*G14 -> 2982.6157 | H28: =H27*H14 -> 3146.4101
A29: Net income (adjusted) | B29: $mm | C29: =C31*C30 -> 8740.08 | D29: =D27-D28 -> 9102.4653 | E29: =E27-E28 -> 9548.9745 | F29: =F27-F28 -> 9912.6627 | G29: =G27-G28 -> 10574.728 | H29: =H27-H28 -> 11155.454
A30: Weighted avg diluted shares | B30: mm | C30: =Historical_5Y!G26 -> 716.4 | D30: =C30*(1+D16) -> 710.6688 | E30: =D30*(1+E16) -> 704.98345 | F30: =E30*(1+F16) -> 699.34358 | G30: =F30*(1+G16) -> 693.74883 | H30: =G30*(1+H16) -> 688.19884
A31: Diluted EPS (adjusted) | B31: $/sh | C31: =Historical_5Y!G20 -> 12.2 | D31: =D29/D30 -> 12.808309 | E31: =E29/E30 -> 13.544963 | F31: =F29/F30 -> 14.174238 | G31: =G29/G30 -> 15.242877 | H31: =H29/H30 -> 16.209638 | I31: Adjusted basis kept for P/E because peer forward P/Es are built on consensus (adjusted) EPS. FY26E check: H1-26 adj. $6.21 (release p.3) + H2-25 $6.34 x ~1.05 = ~$12.9.
A32: EPS growth | B32: % | D32: =D31/C31-1 -> 0.049861355 | E32: =E31/D31-1 -> 0.057513774 | F32: =F31/E31-1 -> 0.046458285 | G32: =G31/F31-1 -> 0.075393034 | H32: =H31/G31-1 -> 0.063423747
A34: C. UNLEVERED FREE CASH FLOW (feeds the DCF)
A35: Operating income (adjusted) | B35: $mm | D35: =D22 -> 13330.927 | E35: =E22 -> 13969.819 | F35: =F22 -> 14505.188 | G35: =G22 -> 15407.889 | H35: =H22 -> 16207.925
A36: Less: restructuring & special charges | B36: $mm | D36: =-D17 -> -250 | E36: =-E17 -> -100 | F36: =-F17 -> 0 | G36: =-G17 -> 0 | H36: =-H17 -> 0 | I36: Cash cost; tax-deductible, so it also lowers taxes below.
A37: EBIT used in DCF | B37: $mm | D37: =D35+D36 -> 13080.927 | E37: =E35+E36 -> 13869.819 | F37: =F35+F36 -> 14505.188 | G37: =G35+G36 -> 15407.889 | H37: =H35+H36 -> 16207.925
A38: Less: taxes on EBIT | B38: $mm | D38: =-D37*D14 -> -2877.804 | E38: =-E37*E14 -> -3051.3602 | F38: =-F37*F14 -> -3191.1413 | G38: =-G37*G14 -> -3389.7356 | H38: =-H37*H14 -> -3565.7436 | I38: EBIT x tax rate - no interest tax shield (it sits in the WACC).
A39: NOPAT | B39: $mm | D39: =D37+D38 -> 10203.123 | E39: =E37+E38 -> 10818.459 | F39: =F37+F38 -> 11314.046 | G39: =G37+G38 -> 12018.154 | H39: =H37+H38 -> 12642.182
A40: Plus: D&A | B40: $mm | D40: =D24 -> 2325.8214 | E40: =E24 -> 2370.636 | F40: =F24 -> 2422.2255 | G40: =G24 -> 2523.959 | H40: =H24 -> 2629.9653
A41: Less: capital expenditures | B41: $mm | C41: =-Historical_5Y!G32 -> -3365 | D41: =-D12 -> -3800 | E41: =-E12 -> -3450 | F41: =-F12 -> -3450 | G41: =-G12 -> -3450 | H41: =-H12 -> -3450
A42: Plus/(less): working capital & other items | B42: $mm | D42: =D21*D13 -> -283.63675 | E42: =E21*E13 -> -282.21857 | F42: =F21*F13 -> -281.65413 | G42: =G21*G13 -> -293.4836 | H42: =H21*H13 -> -305.80991
A43: Unlevered free cash flow (UFCF) - DCF basis, before interest | B43: $mm | D43: =SUM(D39:D42) -> 8445.3079 | E43: =SUM(E39:E42) -> 9456.8762 | F43: =SUM(F39:F42) -> 10004.618 | G43: =SUM(G39:G42) -> 10798.629 | H43: =SUM(H39:H42) -> 11516.337 | I43: UFCF = NOPAT + D&A - capex - working capital, after restructuring cash costs and before interest; it feeds the DCF. NOT comparable with the company "free cash flow" (row 46). Rent on leases stays in operating costs, so lease liabilities are not deducted in the bridge (DCF guide Key Rules #6, #13).
A44: UFCF growth | B44: % | E44: =E43/D43-1 -> 0.11977875 | F44: =F43/E43-1 -> 0.05791992 | G44: =G43/F43-1 -> 0.079364467 | H44: =H43/G43-1 -> 0.066462908 | I44: Should trend toward the terminal growth rate by FY2030 (DCF guide Key Rule #6) - see DCF checks.
A45: Memo: capex % of revenue | B45: % | C45: =-C41/C21 -> 0.12516273 | D45: =-D41/D21 -> 0.13397418 | E45: =-E41/E21 -> 0.12224568 | F45: =-F41/F21 -> 0.12249066 | G45: =-G41/G21 -> 0.11755342 | H45: =-H41/H21 -> 0.11281518 | I45: Must stay above D&A % for a growing company (DCF guide Key Rule #4).
A46: Memo: free cash flow, company definition proxy (CFO - capex ~ UFCF - after-tax interest) | B46: $mm | C46: =Historical_5Y!G33 -> 7186 | D46: =D43-D26*(1-D14) -> 7149.6499 | E46: =E43-E26*(1-E14) -> 8109.3919 | F46: =F43-F26*(1-F14) -> 8603.2341 | G46: =G43-G26*(1-G14) -> 9355.2037 | H46: =H43-H26*(1-H14) -> 10029.609 | I46: Company definition (10-K p.7): cash from operations less capex. FY25A $7,186m.
A47: Memo: FCF / adjusted net income (not the company ratio) | B47: % | D47: =D46/D29 -> 0.78546302 | E47: =E46/E29 -> 0.84924218 | F47: =F46/F29 -> 0.86790344 | G47: =G46/G29 -> 0.88467556 | H47: =H46/H29 -> 0.89907675 | I47: Guidance: low-to-mid 80s% today, mid-to-high 80s% by 2030 (Investor Day).
A48: Memo: GAAP net income (adj. NI less after-tax restructuring) | B48: $mm | C48: =Historical_5Y!G18 -> 8563 | D48: =D29-D17*(1-D14) -> 8907.4653 | E48: =E29-E17*(1-E14) -> 9470.9745 | F48: =F29-F17*(1-F14) -> 9912.6627 | G48: =G29-G17*(1-G14) -> 10574.728 | H48: =H29-H17*(1-H14) -> 11155.454
A49: Memo: FCF conversion - company definition (FCF / GAAP net income) | B49: % | C49: =C46/C48 -> 0.83919187 | D49: =D46/D48 -> 0.80265818 | E49: =E46/E48 -> 0.85623627 | F49: =F46/F48 -> 0.86790344 | G49: =G46/G48 -> 0.88467556 | H49: =H46/H48 -> 0.89907675 | I49: Company definition (10-K p.7): FCF / net income; 84% in 2025 and 81% in 2024 (10-K p.30). Guidance: low-to-mid 80% in 2026, mid-to-high 80% by 2030 (Investor Day).

Sheet Market_WACC
A1: Market data & WACC inputs
A2: Blue = market data at the official 24-Sep-2026 close. Black = formula. Lavender label = changed after the 25-26 Sep reviews (see Model_Review).
A4: Item | B4: Value | C4: Unit | D4: Source / note
A5: MCD MARKET DATA
A6: Share price | B6: 237.02 | C6: $ | D6: REVISED (feedback): official close 24-Sep-2026 (open $239.70, range $237.02-$242.56, -0.55%). Stock Analysis history page (S&P Global Market Intelligence data), stockanalysis.com/stocks/mcd/history, accessed 25-Sep-2026. Previous version used a 9:56am intraday print of $240.09.
A7: Price date | B7: 46289
A8: Shares outstanding | B8: 707.64 | C8: mm | D8: Stock Analysis (S&P Global Market Intelligence data), stockanalysis.com/stocks/mcd/statistics, 24-Sep-2026
A9: Market cap (price x shares) | B9: =B6*B8 -> 167724.83 | C9: $mm | D9: Formula. The source showed $169.90bn at the 9:56am intraday price.
A10: Beta (5-year, monthly) | B10: 0.41 | D10: Stock Analysis (S&P Global Market Intelligence data), stockanalysis.com/stocks/mcd/statistics, 24-Sep-2026. Low beta = defensive stock; betas differ by provider and window, so check Yahoo/Koyfin too.
A11: 10-year US Treasury yield | B11: 0.0518 | C11: % | D11: REVISED 26-Sep (round 4): 10-year Treasury constant maturity at the 24-Sep-2026 close, 5.18% (FRED DGS10 / Fed H.15, from Treasury's par curve), so every market input shares the price date. Was 5.10% (23-Sep; Treasury par curve 5.11%).
A12: Intraday price when source multiples were captured | B12: 240.09 | C12: $ | D12: Stock Analysis statistics page, 24-Sep-2026 9:56am ET. Rows 14-16 were captured at this price; MCD multiples at the close are rescaled on Peers row 13 and computed on Comps D36:D37.
A13: SOURCE MULTIPLES AS CAPTURED AT THE INTRADAY PRICE (cross-check only, not used in the valuation)
A14: P/E (trailing 12 months) | B14: 19.36 | C14: x | D14: Stock Analysis (S&P Global Market Intelligence data), stockanalysis.com/stocks/mcd/statistics, 24-Sep-2026
A15: P/E (forward) | B15: 18.03 | C15: x | D15: Stock Analysis (S&P Global Market Intelligence data), stockanalysis.com/stocks/mcd/statistics, 24-Sep-2026
A16: EV / EBITDA (trailing) | B16: 14.9 | C16: x | D16: Stock Analysis (S&P Global Market Intelligence data), stockanalysis.com/stocks/mcd/statistics, 24-Sep-2026 (source EV includes leases)
A17: Dividend yield (forward dividend / close) | B17: =B18/B6 -> 0.032571091 | C17: % | D17: REVISED (feedback): formula instead of the source yield (3.22% at the intraday price).
A18: Annual dividend per share (forward) | B18: 7.72 | C18: $ | D18: Stock Analysis statistics, 24-Sep-2026: $7.72 annualised (4 x $1.93).
A19: WACC: see the WACC tab (7.56%, bottom-up beta from franchise-heavy peers). The Step-2 starter WACC that stood here was removed in v6.
A30: ENTERPRISE VALUE (own calculation, FY25 balance sheet)
A31: EV excl. leases (mkt cap + net debt) | B31: =B9+Historical_5Y!G46 -> 206923.83 | C31: $mm | D31: Formula
A32: EV incl. leases | B32: =B9+Historical_5Y!G48 -> 221764.83 | C32: $mm | D32: Formula; closer to data-provider EV definitions
A33: EV (excl. leases) / FY25 EBITDA | B33: =B31/Historical_5Y!G23 -> 14.180635 | C33: x | D33: Formula
A34: P/E on FY25 non-GAAP EPS | B34: =B6/Historical_5Y!G20 -> 19.427869 | C34: x | D34: Formula

Sheet WACC
A1: WACC - primary: bottom-up beta from franchise-heavy peers; other beta methods shown as sensitivities
A2: Blue on yellow = assumption. Green = link. Lavender = changed after the 25-26 Sep reviews. Round 3 (26-Sep beta note): base beta = mean unlevered beta of YUM, QSR, DPZ relevered to MCD (rows 44-50); the three earlier methods are now cross-checks.
A4: Item | B4: Value | C4: Unit | D4: Source / note
A5: MARKET INPUTS & CAPITAL STRUCTURE
A6: Risk-free rate (10-year U.S. Treasury) | B6: =Market_WACC!B11 -> 0.0518 | C6: % | D6: Market_WACC B11 (5.18%, 24-Sep-2026 close).
A7: Raw beta (5-year monthly) | B7: =Market_WACC!B10 -> 0.41 | D7: Market_WACC
A8: Share price | B8: =Market_WACC!B6 -> 237.02 | C8: $ | D8: Market_WACC, 24-Sep-2026
A9: Basic shares outstanding | B9: =Market_WACC!B8 -> 707.64 | C9: mm | D9: 707,641,531 at 30-Jun-2026 (10-Q cover).
A10: Dilutive securities (treasury stock method) | B10: 2 | C10: mm | D10: NEW: MCD 10-Q Q2-2026 - TSM dilution of 2.0m shares for the quarter. Multiples guide Key Rule #2: value per share uses diluted shares.
A11: Diluted shares outstanding | B11: =B9+B10 -> 709.64 | C11: mm | D11: Used in DCF, comps and the equity weight.
A12: Market value of equity (diluted) | B12: =B8*B11 -> 168198.87 | C12: $mm
A13: Market value of debt (fair value, 30-Jun-2026) | B13: =DCF!B12 -> 38300 | C13: $mm | D13: REVISED: 10-Q fair value $38.3bn vs carrying $39.9bn (multiples guide Key Rule #10 - use market values). Leases excluded, as rent is in the FCF.
A14: Tax rate | B14: =Forecast!D14 -> 0.22 | C14: % | D14: Forecast
A15: MCD debt / equity (market) | B15: =B13/B12 -> 0.22770664
A17: COST OF EQUITY (CAPM) - earlier three methods, now cross-checks (primary method in rows 44-50)
A18: Equity risk premium | B18: 0.05 | C18: % | D18: ASSUMPTION: 5.0%, inside the 4-6% range the guide cites (it used 5.5% in its example).
A19: Blume weight on raw beta | B19: 0.67 | D19: Standard Blume adjustment: 0.67 x raw + 0.33.
A20: Method 1 beta: historical (Blume-adjusted) | B20: =B19*B7+(1-B19) -> 0.6047 | D20: Guide method 3 ("easy method"): company's own historical beta.
A21: Peer median unlevered beta | B21: =Comps!M11 -> 0.68894443 | D21: Comps tab: each peer beta / (1 + D/E x (1 - t)), D/E excluding operating leases.
A22: Method 2 beta: peers re-levered at MCD current D/E | B22: =B21*(1+B15*(1-B14)) -> 0.81130866 | D22: Guide method 1.
A23: Peer median debt / total capital | B23: =Comps!O11 -> 0.2362234 | C23: % | D23: Proxy for a "target" capital structure (guide method 2).
A24: Method 3 beta: peers re-levered at peer-median structure | B24: =B21*(1+B23/(1-B23)*(1-B14)) -> 0.8551461 | D24: Guide method 2.
A25: Cost of equity - method 1 | B25: =B6+B20*B18 -> 0.082035 | C25: %
A26: Cost of equity - method 2 | B26: =B6+B22*B18 -> 0.092365433 | C26: %
A27: Cost of equity - method 3 | B27: =B6+B24*B18 -> 0.094557305 | C27: %
A29: COST OF DEBT
A30: Credit spread over 10-year Treasury | B30: 0.009 | C30: % | D30: ASSUMPTION: ~90bp for BBB+/Baa1 long bonds (guide: risk-free + default spread). Check: fair value below carrying implies market yields above coupons.
A31: Pre-tax cost of debt | B31: =B6+B30 -> 0.0608 | C31: %
A32: After-tax cost of debt | B32: =B31*(1-B14) -> 0.047424 | C32: %
A34: WACC - earlier methods (cross-checks) and the WACC used
A35: Equity weight - current market structure | B35: =B12/(B12+B13) -> 0.81452683 | C35: %
A36: WACC - method 1 (historical beta, current structure) | B36: =B35*B25+(1-B35)*B32 -> 0.075615588 | C36: %
A37: WACC - method 2 (peer beta, current structure) | B37: =B35*B26+(1-B35)*B32 -> 0.084030003 | C37: %
A38: WACC - method 3 (peer beta, peer-median structure) | B38: =(1-B23)*B27+B23*B32 -> 0.083423315 | C38: %
A39: WACC used (primary: franchise-heavy bottom-up beta, row 50) | B39: =B50 -> 0.075573866 | C39: % | D39: REVISED 26-Sep (beta note): was the equal-weight average of methods 1-3 (8.03%), which had no economic basis. Now the WACC from the bottom-up franchise-heavy beta; all other estimates are sensitivities (rows 52-64).
A40: Memo: range of the three earlier methods (low / high) | B40: =MIN(B36:B38) -> 0.075615588 | C40: =MAX(B36:B38) -> 0.084030003 | D40: Low in column B, high in column C.
A41: Memo: franchise-heavy MEDIAN beta relevered, WACC (= low case, row 54) | B41: =B35*(B6+Comps!M14*(1+B15*(1-B14))*B18)+(1-B35)*B32 -> 0.07223959 | C41: % | D41: Shows how much SBUX/CMG (company-operated, higher beta) lift the peer beta.
A42: Memo: book equity 30-Jun-2026 (not used) | B42: -1023 | C42: $mm | D42: 10-Q: negative after decades of buybacks, so book weights are meaningless.
A44: PRIMARY BETA - BOTTOM-UP FROM FRANCHISE-HEAVY PEERS (>= 90% of restaurants franchised: YUM, QSR, DPZ)
A45: Mean unlevered beta, franchise-heavy peers | B45: =AVERAGE(Comps!M6,Comps!M7,Comps!M10) -> 0.51262722 | D45: Each peer's 5Y monthly beta unlevered at its market D/E excl. operating leases (Comps col. M). Mean, not median: with three peers the median ignores DPZ's higher operating risk from its supply chain.
A46: Relevering factor to MCD: 1 + (1 - t) x D/E | B46: =1+(1-B14)*B15 -> 1.1776112 | D46: MCD D/E = fair-value debt / diluted market cap (B15), 24-Sep close.
A47: PRIMARY BETA (relevered to MCD) | B47: =B45*B46 -> 0.60367555 | D47: About 0.60. Cross-check: MCD's own Blume-adjusted beta is also 0.60 (B20), so two independent routes agree.
A48: Cost of equity - primary | B48: =B6+B47*B18 -> 0.081983777 | D48: rf + beta x ERP
A49: After-tax cost of debt | B49: =B32 -> 0.047424 | D49: Unchanged: 5.18% + 0.90% spread, after 22% tax.
A50: WACC - primary (market-value weights, current structure) | B50: =B35*B48+(1-B35)*B49 -> 0.075573866 | D50: Feeds B39 and the DCF.
A52: BETA SENSITIVITIES AND CROSS-CHECKS (not in the base case)
A53: Beta estimate | B53: Beta | C53: WACC | D53: Role
A54: Franchise-heavy MEDIAN unlevered beta, relevered | B54: =Comps!M14*B46 -> 0.5218053 | C54: =$B$35*($B$6+B54*$B$18)+(1-$B$35)*$B$32 -> 0.07223959 | D54: Low case: the median of three is just YUM and discards DPZ.
A55: PRIMARY: franchise-heavy MEAN unlevered beta, relevered | B55: =B47 -> 0.60367555 | C55: =B50 -> 0.075573866 | D55: Base case.
A56: Conservative blend: B66 on franchise-heavy, rest on all five | B56: =B66*B47+(1-B66)*B57 -> 0.65193856 | C56: =$B$35*($B$6+B56*$B$18)+(1-$B$35)*$B$32 -> 0.077539442 | D56: Alternative if extra caution is wanted (~0.65).
A57: All five peers: MEAN unlevered beta, relevered | B57: =AVERAGE(Comps!M6:M10)*B46 -> 0.79672762 | C57: =$B$35*($B$6+B57*$B$18)+(1-$B$35)*$B$32 -> 0.083436171 | D57: High case (~0.80): SBUX and CMG carry company-operated risk MCD does not.
A58: All five peers: median unlevered, relevered (earlier method 2) | B58: =B22 -> 0.81130866 | C58: =B37 -> 0.084030003 | D58: Earlier method 2.
A59: All five: median unlevered at peer-median D/Cap (earlier method 3) | B59: =B24 -> 0.8551461 | C59: =B38 -> 0.083423315 | D59: Earlier method 3; uses 23% debt / capital, which is why the old 8.04% average cannot be rebuilt with an 18% weight.
A60: MCD historical beta, Blume-adjusted (earlier method 1) | B60: =B20 -> 0.6047 | C60: =B36 -> 0.075615588 | D60: Cross-check: equals the primary beta.
A61: MCD raw 5-year monthly beta | B61: =B7 -> 0.41 | C61: =$B$35*($B$6+B61*$B$18)+(1-$B$35)*$B$32 -> 0.067686169 | D61: Lower-bound cross-check only: one regression, sensitive to period and frequency.
A62: Raw median of the five peer levered betas | B62: =Comps!L11 -> 0.94 | C62: =$B$35*($B$6+B62*$B$18)+(1-$B$35)*$B$32 -> 0.089271131 | D62: Not used: the median is CMG, a company-operated fast-casual chain.
A63: Broad U.S. restaurant sector (Damodaran), levered | B63: 0.92 | C63: =$B$35*($B$6+B63*$B$18)+(1-$B$35)*$B$32 -> 0.088456604 | D63: Outer bound. Figure taken from the beta treatment note, not independently verified.
A64: Earlier base: equal-weight average of methods 1-3 | C64: =AVERAGE(B36:B38) -> 0.081022969 | D64: Replaced 26-Sep.
A66: Blend weight on the franchise-heavy beta (row 56) | B66: 0.75 | D66: Beta treatment note: 75% franchise-heavy / 25% all peers.
A68: BETA RECONCILIATION (report footnote)
A69: 0.41 = MCD raw 5-year monthly beta vs the S&P 500 (Market_WACC B10); shown on page 1 of the report, used only as a cross-check.
A70: 0.60 = WACC beta: YUM, QSR and DPZ betas unlevered at market D/E excluding operating leases (as in the DCF), averaged, relevered at MCD's D/E. MCD's Blume-adjusted own beta is also 0.60.
A71: 0.52 / 0.65 / 0.80 = franchise-heavy median, 75/25 blend and all-five-peer mean: sensitivities.
A72: Data: all betas are 5Y monthly from one provider (Stock Analysis / S&P Global); all prices and market caps are 24-Sep closes (round 5). Peers are unlevered with net debt while MCD is relevered at gross fair-value debt (effect < 0.01 on beta).
A74: MCD'S OWN UNLEVERED BETA (for the peer table; added round 4)
A75: MCD raw beta, unlevered at current D/E | B75: =B7/B46 -> 0.34816246 | D75: Comparable with the peer unlevered betas, which are built from raw betas: ~0.35.
A76: MCD Blume-adjusted beta, unlevered | B76: =B20/B46 -> 0.51349716 | D76: ~0.51, the same as the franchise-heavy peer mean.
A77: Memo: WACC beta (relevered equity beta, not unlevered) | B77: =B47 -> 0.60367555 | D77: The 0.60 in the WACC is an equity beta at MCD's capital structure; the peer table must not show it in the unlevered column.

Sheet Comps
A1: Comparable companies - lease-consistent multiples, period-matched to MCD figures
A2: Source multiples from the Peers tab (Stock Analysis, 24-Sep-2026). Blue = inputs. Orange = changed after the guide review. Lavender = changed after the 25-Sep external feedback (see Model_Review rows 26+).
A4: Company | B4: Ticker | C4: Market cap ($bn) | D4: EV incl. leases ($bn) | E4: EV/EBITDA (source) | F4: LTM EBITDA ($bn) | G4: Operating lease liab. ($bn) | H4: EV excl. op. leases ($bn) | I4: EV/EBITDA lease-adjusted | J4: Net debt excl. leases ($bn) | K4: Debt / equity | L4: Levered beta | M4: Unlevered beta | N4: Forward P/E | O4: Debt / capital | P4: Operating-lease source
A6: =Peers!A5 -> Yum! Brands | B6: =Peers!B5 -> YUM | C6: =Peers!E5 -> 37.476958 | D6: =Peers!F5 -> 50.206958 | E6: =Peers!I5 -> 16.471995 | F6: =D6/E6 -> 3.0480192 | G6: 1.139 | H6: =D6-G6 -> 49.067958 | I6: =H6/F6 -> 16.09831 | J6: =H6-C6 -> 11.591 | K6: =MAX(0,J6/C6) -> 0.30928337 | L6: =Peers!J5 -> 0.55 | M6: =L6/(1+K6*(1-Forecast!$D$14)) -> 0.44310491 | N6: =Peers!H5 -> 21.570181 | O6: =K6/(1+K6) -> 0.2362234 | P6: YUM 10-Q 30-Jun-2026: non-current operating lease liabilities $1,139m (current portion sits in accrued liabilities, not separately retrieved).
A7: =Peers!A6 -> Restaurant Brands Intl. | B7: =Peers!B6 -> QSR | C7: =Peers!E6 -> 32.229119 | D7: =Peers!F6 -> 46.779119 | E7: =Peers!I6 -> 16.003383 | F7: =D7/E7 -> 2.9230769 | G7: 1.908 | H7: =D7-G7 -> 44.871119 | I7: =H7/F7 -> 15.350646 | J7: =H7-C7 -> 12.642 | K7: =MAX(0,J7/C7) -> 0.39225397 | L7: =Peers!J6 -> 0.53 | M7: =L7/(1+K7*(1-Forecast!$D$14)) -> 0.40583232 | N7: =Peers!H6 -> 16.713228 | O7: =K7/(1+K7) -> 0.28174024 | P7: QSR 10-Q 30-Jun-2026: operating lease liabilities, net of current portion $1,908m (current portion in other accrued liabilities).
A8: =Peers!A7 -> Starbucks | B8: =Peers!B7 -> SBUX | C8: =Peers!E7 -> 106.74107 | D8: =Peers!F7 -> 125.58107 | E8: =Peers!I7 -> 22.289195 | F8: =D8/E8 -> 5.6341682 | G8: 9 | H8: =D8-G8 -> 116.58107 | I8: =H8/F8 -> 20.691799 | J8: =H8-C8 -> 9.84 | K8: =MAX(0,J8/C8) -> 0.092185694 | L8: =Peers!J7 -> 0.97 | M8: =L8/(1+K8*(1-Forecast!$D$14)) -> 0.90493107 | N8: =Peers!H7 -> 31.850963 | O8: =K8/(1+K8) -> 0.08440478 | P8: ESTIMATE: SBUX had $10.3bn at Dec-2024 (current $1.45bn + LT $8.86bn); China retail operations divested in FQ3-2026. Exact Jun-2026 figure not retrieved - does not change the median.
A9: =Peers!A8 -> Chipotle Mexican Grill | B9: =Peers!B8 -> CMG | C9: =Peers!E8 -> 40.504274 | D9: =Peers!F8 -> 45.244274 | E9: =Peers!I8 -> 20.161588 | F9: =D9/E9 -> 2.2440828 | G9: 5.246 | H9: =D9-G9 -> 39.998274 | I9: =H9/F9 -> 17.823885 | J9: =H9-C9 -> -0.506 | K9: =MAX(0,J9/C9) -> 0 | L9: =Peers!J8 -> 0.94 | M9: =L9/(1+K9*(1-Forecast!$D$14)) -> 0.94 | N9: =Peers!H8 -> 25.621909 | O9: =K9/(1+K9) -> 0 | P9: CMG 10-Q 31-Mar-2026: current $310m + long-term $4,936m.
A10: =Peers!A9 -> Domino's Pizza | B10: =Peers!B9 -> DPZ | C10: =Peers!E9 -> 9.697481 | D10: =Peers!F9 -> 14.647481 | E10: =Peers!I9 -> 14.319997 | F10: =D10/E10 -> 1.022869 | G10: 0.239 | H10: =D10-G10 -> 14.408481 | I10: =H10/F10 -> 14.08634 | J10: =H10-C10 -> 4.711 | K10: =MAX(0,J10/C10) -> 0.48579626 | L10: =Peers!J9 -> 0.95 | M10: =L10/(1+K10*(1-Forecast!$D$14)) -> 0.68894443 | N10: =Peers!H9 -> 14.481967 | O10: =K10/(1+K10) -> 0.32696021 | P10: DPZ 14-Jun-2026: current $46m + long-term $193m (Stock Analysis balance sheet).
A11: Peer median | E11: =MEDIAN(E6:E10) -> 16.471995 | I11: =MEDIAN(I6:I10) -> 16.09831 | K11: =MEDIAN(K6:K10) -> 0.30928337 | L11: =MEDIAN(L6:L10) -> 0.94 | M11: =MEDIAN(M6:M10) -> 0.68894443 | N11: =MEDIAN(N6:N10) -> 21.570181 | O11: =MEDIAN(O6:O10) -> 0.2362234 | P11: Unlevering uses D/E excluding operating leases, consistent with not treating leases as capital (DCF guide Key Rule #5). One tax rate (22%) applied to all peers for simplicity.
A12: Peer 25th percentile | E12: =PERCENTILE(E6:E10,0.25) -> 16.003383 | I12: =PERCENTILE(I6:I10,0.25) -> 15.350646 | K12: =PERCENTILE(K6:K10,0.25) -> 0.092185694 | L12: =PERCENTILE(L6:L10,0.25) -> 0.55 | M12: =PERCENTILE(M6:M10,0.25) -> 0.44310491 | N12: =PERCENTILE(N6:N10,0.25) -> 16.713228 | O12: =PERCENTILE(O6:O10,0.25) -> 0.08440478
A13: Peer 75th percentile | E13: =PERCENTILE(E6:E10,0.75) -> 20.161588 | I13: =PERCENTILE(I6:I10,0.75) -> 17.823885 | K13: =PERCENTILE(K6:K10,0.75) -> 0.39225397 | L13: =PERCENTILE(L6:L10,0.75) -> 0.95 | M13: =PERCENTILE(M6:M10,0.75) -> 0.90493107 | N13: =PERCENTILE(N6:N10,0.75) -> 25.621909 | O13: =PERCENTILE(O6:O10,0.75) -> 0.28174024
A14: Franchise-heavy median (YUM, QSR, DPZ) - PRIMARY | E14: =MEDIAN(E6,E7,E10) -> 16.003383 | I14: =MEDIAN(I6,I7,I10) -> 15.350646 | K14: =MEDIAN(K6,K7,K10) -> 0.39225397 | L14: =MEDIAN(L6,L7,L10) -> 0.55 | M14: =MEDIAN(M6,M7,M10) -> 0.44310491 | N14: =MEDIAN(N6,N7,N10) -> 16.713228 | O14: =MEDIAN(O6,O7,O10) -> 0.28174024
A15: Franchise-heavy MEAN (YUM, QSR, DPZ) - used for the WACC beta | K15: =AVERAGE(K6,K7,K10) -> 0.39577787 | L15: =AVERAGE(L6,L7,L10) -> 0.67666667 | M15: =AVERAGE(M6,M7,M10) -> 0.51262722 | O15: =AVERAGE(O6,O7,O10) -> 0.28164129
A16: MCD METRICS (period-matched to each multiple)
A17: LTM operating income (GAAP) to 30-Jun-2026 | B17: $mm | C17: =Historical_5Y!G15+Reference_Data!I31-Reference_Data!H31 -> 12805 | P17: FY25 + H1-26 - H1-25 (multiples guide Key Rule #15). GAAP, because the source EBITDA for peers is unadjusted and MCD's restructuring has recurred for four years.
A18: H1-2026 D&A (cash flow statement) | B18: $mm | C18: 1131 | P18: MCD 10-Q Q2-2026, cash flow statement.
A19: H1-2025 D&A (cash flow statement) | B19: $mm | C19: 1064 | P19: MCD 10-Q Q2-2026, cash flow statement (prior-year column).
A20: LTM D&A | B20: $mm | C20: =Historical_5Y!G22+C18-C19 -> 2266
A21: LTM EBITDA (GAAP) | B21: $mm | C21: =C17+C20 -> 15071 | P21: Cross-check: Stock Analysis EV $223.68bn / 14.9x = $15.0bn.
A22: Weight of FY2026E in next twelve months | B22: % | C22: =(DATE(2026,12,31)-Market_WACC!B7)/365 -> 0.26849315 | P22: (31-Dec-2026 - price date) / 365.
A23: NTM diluted EPS (adjusted) | B23: $/sh | C23: =C22*Forecast!D31+(1-C22)*Forecast!E31 -> 13.347176 | P23: Calendarised: w x FY26E + (1 - w) x FY27E (multiples guide Key Rule #16). Adjusted to match consensus-based forward P/E.
A24: Net debt (fair-value debt less cash, 30-Jun-2026) | B24: $mm | C24: =DCF!B13 -> 37478 | P24: DCF tab - same bridge as the DCF. Leases excluded because EBITDA is after rent (lease-adjusted multiples above).
A25: Diluted shares | B25: mm | C25: =WACC!B11 -> 709.64 | P25: WACC tab (basic + treasury-stock dilution).
A27: IMPLIED VALUE PER SHARE - PRIMARY SET: FRANCHISE-HEAVY PEERS (YUM, QSR, DPZ)
A28: Method | C28: Low (min) | D28: Median | E28: High (max) | F28: Weight | P28: Note
A29: Forward P/E x NTM EPS | C29: =MIN(N6,N7,N10)*$C$23 -> 193.29336 | D29: =N14*$C$23 -> 223.07439 | E29: =MAX(N6,N7,N10)*$C$23 -> 287.901 | F29: 0.5 | P29: REVISED (feedback): franchise-heavy peer forward P/E (min / median / max of YUM, QSR, DPZ) x MCD NTM EPS. SBUX and CMG are company-operated and priced on faster growth, so they no longer set the target (all-five result kept in row 34).
A30: LTM EV/EBITDA (lease-adjusted) x LTM EBITDA | C30: =(MIN(I6,I7,I10)*$C$21-$C$24)/$C$25 -> 246.34636 | D30: =(I14*$C$21-$C$24)/$C$25 -> 273.1971 | E30: =(MAX(I6,I7,I10)*$C$21-$C$24)/$C$25 -> 289.07563 | F30: =1-F29 -> 0.5 | P30: REVISED (feedback): franchise-heavy peers only. Trailing multiple on MCD LTM EBITDA (period-matched); EV excludes operating leases to pair with post-rent EBITDA (multiples guide Key Rules #8, #9).
A31: Comps value per share (weighted) - used in the target | C31: =C29*$F$29+C30*$F$30 -> 219.81986 | D31: =D29*$F$29+D30*$F$30 -> 248.13575 | E31: =E29*$F$29+E30*$F$30 -> 288.48831 | P31: Why 50/50 (round 4): EV/EBITDA is capital-structure neutral, which matters because the franchise-heavy peers carry more debt than MCD, but it ignores D&A and capex, and MCD owns much of its real estate, which flatters it on EBITDA. Forward P/E captures D&A, interest and tax and is forward-looking, but is distorted by the peers' higher leverage. The biases run in opposite directions and neither clearly dominates, so each gets half; the DCF (60%) remains the anchor.
A33: MEMO / CROSS-CHECKS (not used in the target)
A34: All five peers (previous primary set): 25th / median / 75th | C34: =(N12*$C$23)*$F$29+((I12*$C$21-$C$24)/$C$25)*$F$30 -> 248.13575 | D34: =(N11*$C$23)*$F$29+((I11*$C$21-$C$24)/$C$25)*$F$30 -> 288.48831 | E34: =(N13*$C$23)*$F$29+((I13*$C$21-$C$24)/$C$25)*$F$30 -> 333.85135 | P34: What the target used before the feedback review (median $292.69). Shows how much company-operated SBUX and CMG lift the peer set.
A35: Previous method: source EV/EBITDA x NTM EBITDA | D35: =(E11*(C22*Forecast!D25+(1-C22)*Forecast!E25)-(C24+DCF!B14))/C25 -> 301.46148 | P35: What the model did before the review: trailing multiple on forward EBITDA and lease-inclusive EV - mismatched on both period and leases.
A36: MCD at current price: forward P/E (NTM) | D36: =Market_WACC!B6/C23 -> 17.758063 | P36: vs franchise-heavy median in N14 (all-peer median in N11).
A37: MCD at current price: LTM EV/EBITDA (excl. op. leases) | D37: =(WACC!B12+C24)/C21 -> 13.647195 | P37: vs franchise-heavy median in I14 (all-peer median in I11).
A39: PEER GROWTH & BUSINESS MODEL - why the franchise-heavy set is primary (added after feedback)
A40: Company | B40: Ticker | C40: Forward P/E | D40: Trailing P/E | E40: Implied NTM EPS growth | F40: EV/EBITDA (lease-adj.) | G40: Primary set? | P40: Business model / note
A41: =A6 -> Yum! Brands | B41: =B6 -> YUM | C41: =N6 -> 21.570181 | D41: =Peers!G5 -> 17.443283 | E41: =D41/C41-1 -> -0.1913242 | F41: =I6 -> 16.09831 | G41: Yes | P41: Franchise-heavy: ~97% franchised at end-2025 (beta note, citing YUM 2025 10-K). Implied growth understated: trailing EPS flattered by a one-off tax benefit.
A42: =A7 -> Restaurant Brands Intl. | B42: =B7 -> QSR | C42: =N7 -> 16.713228 | D42: =Peers!G6 -> 19.12769 | E42: =D42/C42-1 -> 0.14446418 | F42: =I7 -> 15.350646 | G42: Yes | P42: Franchise-heavy (Burger King, Tim Hortons, Popeyes, Firehouse); predominantly franchised.
A43: =A8 -> Starbucks | B43: =B8 -> SBUX | C43: =N8 -> 31.850963 | D43: =Peers!G7 -> 53.868676 | E43: =D43/C43-1 -> 0.69127307 | F43: =I8 -> 20.691799 | G43: No | P43: Mostly company-operated; 7,991 China stores moved to licensed in 2026 (beta note) but still far less franchise-intensive. Implied growth overstated: trailing EPS depressed by restructuring.
A44: =A9 -> Chipotle Mexican Grill | B44: =B9 -> CMG | C44: =N9 -> 25.621909 | D44: =Peers!G8 -> 30.122384 | E44: =D44/C44-1 -> 0.17564948 | F44: =I9 -> 17.823885 | G44: No | P44: Almost entirely company-operated.
A45: =A10 -> Domino's Pizza | B45: =B10 -> DPZ | C45: =N10 -> 14.481967 | D45: =Peers!G9 -> 16.597422 | E45: =D45/C45-1 -> 0.14607509 | F45: =I10 -> 14.08634 | G45: Yes | P45: ~99% franchised, but runs a large supply chain (~$3.0bn of ~$4.9bn 2025 revenue, beta note): explains its higher beta.
A46: McDonald's (24-Sep close) | B46: MCD | C46: =Peers!H13 -> 17.799453 | D46: =Peers!G13 -> 19.112446 | E46: =D46/C46-1 -> 0.073765946 | F46: =D37 -> 13.647195 | P46: MCD forward P/E is the source consensus multiple rescaled to the close; EV/EBITDA is the model figure (excl. operating leases).
A47: Franchise-heavy median | C47: =MEDIAN(C41,C42,C45) -> 16.713228 | D47: =MEDIAN(D41,D42,D45) -> 17.443283 | E47: =MEDIAN(E41,E42,E45) -> 0.14446418 | F47: =MEDIAN(F41,F42,F45) -> 15.350646
A48: Reading: implied NTM EPS growth = trailing P/E / forward P/E - 1 (same price, so it equals forward EPS / trailing EPS - 1). On the clean readings QSR and DPZ are expected to grow EPS ~14-15% vs ~7% for MCD, so even the franchise-heavy multiple is a generous yardstick for MCD; growth-adjusting would lower the comps value further. That supports dropping the higher all-peer set, not raising the comps weight.

Sheet Peers
A1: Peer multiples - quick-service & fast-casual restaurants
A2: Source: Stock Analysis (S&P Global Market Intelligence). REVISED round 5: every price is the official 24-Sep-2026 close; peer multiples are the source snapshot (rows 29-33) rescaled to that close. Lavender = changed after the feedback reviews.
A4: Company | B4: Ticker | C4: Price ($) | D4: Price as of | E4: Market cap ($bn) | F4: EV ($bn) | G4: P/E trailing | H4: P/E forward | I4: EV/EBITDA trailing | J4: Beta (5Y) | K4: Note
A5: Yum! Brands | B5: YUM | C5: 137.34 | D5: 24-Sep close | E5: =E29*C5/C29 -> 37.476958 | F5: =F29+(E5-E29) -> 50.206958 | G5: =G29*C5/C29 -> 17.443283 | H5: =H29*C5/C29 -> 21.570181 | I5: =F5/(F29/I29) -> 16.471995 | J5: =J29 -> 0.55 | K5: Trailing P/E flattered by a one-off tax benefit (negative TTM tax); use forward P/E
A6: Restaurant Brands Intl. | B6: QSR | C6: 70.91 | D6: 24-Sep close | E6: =E30*C6/C30 -> 32.229119 | F6: =F30+(E6-E30) -> 46.779119 | G6: =G30*C6/C30 -> 19.12769 | H6: =H30*C6/C30 -> 16.713228 | I6: =F6/(F30/I30) -> 16.003383 | J6: =J30 -> 0.53 | K6: Market cap includes exchangeable LP units (454.5m shares)
A7: Starbucks | B7: SBUX | C7: 93.65 | D7: 24-Sep close | E7: =E31*C7/C31 -> 106.74107 | F7: =F31+(E7-E31) -> 125.58107 | G7: =G31*C7/C31 -> 53.868676 | H7: =H31*C7/C31 -> 31.850963 | I7: =F7/(F31/I31) -> 22.289195 | J7: =J31 -> 0.97 | K7: Trailing earnings depressed by turnaround/restructuring costs
A8: Chipotle Mexican Grill | B8: CMG | C8: 32.01 | D8: 24-Sep close | E8: =E32*C8/C32 -> 40.504274 | F8: =F32+(E8-E32) -> 45.244274 | G8: =G32*C8/C32 -> 30.122384 | H8: =H32*C8/C32 -> 25.621909 | I8: =F8/(F32/I32) -> 20.161588 | J8: =J32 -> 0.94 | K8: Company-operated model, net debt mostly leases; post 50:1 split
A9: Domino's Pizza | B9: DPZ | C9: 293.03 | D9: 24-Sep close | E9: =E33*C9/C33 -> 9.697481 | F9: =F33+(E9-E33) -> 14.647481 | G9: =G33*C9/C33 -> 16.597422 | H9: =H33*C9/C33 -> 14.481967 | I9: =F9/(F33/I33) -> 14.319997 | J9: =J33 -> 0.95 | K9: Heavily franchised, highly levered
A10: Peer median | E10: =MEDIAN(E5:E9) -> 37.476958 | F10: =MEDIAN(F5:F9) -> 46.779119 | G10: =MEDIAN(G5:G9) -> 19.12769 | H10: =MEDIAN(H5:H9) -> 21.570181 | I10: =MEDIAN(I5:I9) -> 16.471995 | J10: =MEDIAN(J5:J9) -> 0.94
A11: Peer mean | E11: =AVERAGE(E5:E9) -> 45.329781 | F11: =AVERAGE(F5:F9) -> 56.491781 | G11: =AVERAGE(G5:G9) -> 27.431891 | H11: =AVERAGE(H5:H9) -> 22.047649 | I11: =AVERAGE(I5:I9) -> 17.849232 | J11: =AVERAGE(J5:J9) -> 0.788
A12: Franchise-heavy median (YUM, QSR, DPZ) - primary set | E12: =MEDIAN(E5,E6,E9) -> 32.229119 | F12: =MEDIAN(F5,F6,F9) -> 46.779119 | G12: =MEDIAN(G5,G6,G9) -> 17.443283 | H12: =MEDIAN(H5,H6,H9) -> 16.713228 | I12: =MEDIAN(I5,I6,I9) -> 16.003383 | J12: =MEDIAN(J5,J6,J9) -> 0.55
A13: McDonald's (24-Sep close) | B13: MCD | C13: =Market_WACC!B6 -> 237.02 | D13: 24-Sep close | E13: =Market_WACC!B9/1000 -> 167.72483 | F13: =F24+(E13-E24) -> 221.50483 | G13: =G24*C13/C24 -> 19.112446 | H13: =H24*C13/C24 -> 17.799453 | I13: =F13/(F24/I24) -> 14.755106 | J13: =Market_WACC!B10 -> 0.41 | K13: REVISED (feedback): price links to Market_WACC (24-Sep close). Source multiples were captured at $240.09 (row 24): P/E rescaled by price; EV moved by the change in market cap; EBITDA unchanged.
A14: MCD premium / (discount) vs all-peer median | G14: =G13/G10-1 -> -0.00079697634 | H14: =H13/H10-1 -> -0.17481207 | I14: =I13/I10-1 -> -0.10423083
A15: MCD premium / (discount) vs franchise-heavy median | G15: =G13/G12-1 -> 0.095690875 | H15: =H13/H12-1 -> 0.064991932 | I15: =I13/I12-1 -> -0.078000847
A16: Reading this table:
A17: - Forward P/E is the cleanest comparison: trailing P/E is distorted for YUM (tax benefit) and SBUX (restructuring).
A18: - At the close MCD sits ~19% below the all-peer median on forward P/E (row 14), but only slightly above the franchise-heavy median on P/E and below it on EV/EBITDA (row 15): on the closest business models MCD looks fairly priced, not cheap.
A19: - Business models differ: CMG and SBUX are mostly company-operated (lower margins, higher growth); YUM, QSR and DPZ are franchise-heavy like MCD, so they are the primary set on Comps from this revision.
A20: - Timestamps: every price (peers and MCD) is the official 24-Sep close (round 5); multiples are rescaled from the 23-24 Sep source snapshot, holding EPS, EBITDA and net debt constant.
A21: - The task suggested Koyfin or Yahoo Finance; these came from Stock Analysis because it publishes all the fields on one page.
A23: MEMO: MCD SOURCE SNAPSHOT AS CAPTURED 24-SEP 9:56AM ET (rescaled to the close in row 13)
A24: McDonald's - source snapshot | B24: MCD | C24: =Market_WACC!B12 -> 240.09 | D24: 24-Sep 9:56am | E24: 169.9 | F24: 223.68 | G24: 19.36 | H24: 18.03 | I24: 14.9 | K24: Stock Analysis statistics page as captured (EV includes leases). Kept so the rescaling in row 13 is traceable.
A27: MEMO: PEER SOURCE SNAPSHOT AS CAPTURED (23-Sep close / 24-Sep morning) - rescaled to the 24-Sep close in rows 5-9
A28: Company | B28: Ticker | C28: Price ($) | D28: Captured | E28: Market cap ($bn) | F28: EV ($bn) | G28: P/E trailing | H28: P/E forward | I28: EV/EBITDA trailing | J28: Beta (5Y)
A29: =A5 -> Yum! Brands | B29: =B5 -> YUM | C29: 139.44 | D29: 24-Sep 9:49am | E29: 38.05 | F29: 50.78 | G29: 17.71 | H29: 21.9 | I29: 16.66 | J29: 0.55 | K29: Stock Analysis statistics pages as captured 23-24 Sep. Rows 5-9 take the official 24-Sep closes from the Stock Analysis history pages (S&P Global): P/E rescaled by price; EV moved by the change in market cap; EBITDA, net debt and beta unchanged.
A30: =A6 -> Restaurant Brands Intl. | B30: =B6 -> QSR | C30: 71.66 | D30: 23-Sep close | E30: 32.57 | F30: 47.12 | G30: 19.33 | H30: 16.89 | I30: 16.12 | J30: 0.53
A31: =A7 -> Starbucks | B31: =B7 -> SBUX | C31: 94 | D31: 24-Sep 9:51am | E31: 107.14 | F31: 125.98 | G31: 54.07 | H31: 31.97 | I31: 22.36 | J31: 0.97
A32: =A8 -> Chipotle Mexican Grill | B32: =B8 -> CMG | C32: 32.22 | D32: 24-Sep 9:51am | E32: 40.77 | F32: 45.51 | G32: 30.32 | H32: 25.79 | I32: 20.28 | J32: 0.94
A33: =A9 -> Domino's Pizza | B33: =B9 -> DPZ | C33: 296.43 | D33: 23-Sep close | E33: 9.81 | F33: 14.76 | G33: 16.79 | H33: 14.65 | I33: 14.43 | J33: 0.95

Sheet Historical_5Y
A1: McDonald's - five-year annual history (FY2021-FY2025)
A2: Blue = figure from the 10-Ks (source in column I). Black = formula. $ millions unless stated. Fiscal year ends 31 December.
A4: Line item | B4: Unit | C4: FY2021 | D4: FY2022 | E4: FY2023 | F4: FY2024 | G4: FY2025 | H4: CAGR 21-25 | I4: Source
A5: REVENUE
A6: Revenues from franchised restaurants | B6: $mm | C6: 13085 | D6: 14106 | E6: 15437 | F6: 15715 | G6: 16548 | H6: =IFERROR((G6/C6)^(1/4)-1,"") -> 0.060456715 | I6: 10-K FY2022 (SEC) p.13; 10-K FY2025 (project file) p.39
A7: Sales by company-operated restaurants | B7: $mm | C7: 9787 | D7: 8748 | E7: 9742 | F7: 9782 | G7: 9690 | H7: =IFERROR((G7/C7)^(1/4)-1,"") -> -0.0024870393 | I7: 10-K FY2022 (SEC) p.11; 10-K FY2025 (project file) p.39
A8: Other revenues | B8: $mm | C8: 351 | D8: 329 | E8: 316 | F8: 423 | G8: 647 | H8: =IFERROR((G8/C8)^(1/4)-1,"") -> 0.16519682 | I8: 10-K FY2022 (SEC) p.11; 10-K FY2025 (project file) p.39
A9: Total revenues | B9: $mm | C9: =SUM(C6:C8) -> 23223 | D9: =SUM(D6:D8) -> 23183 | E9: =SUM(E6:E8) -> 25495 | F9: =SUM(F6:F8) -> 25920 | G9: =SUM(G6:G8) -> 26885 | H9: =IFERROR((G9/C9)^(1/4)-1,"") -> 0.037284599 | I9: Formula
A10: Franchised % of total revenue | B10: % | C10: =C6/C9 -> 0.56345003 | D10: =D6/D9 -> 0.6084631 | E10: =E6/E9 -> 0.60549127 | F10: =F6/F9 -> 0.60628858 | G10: =G6/G9 -> 0.61551051 | I10: Formula
A11: Company-operated % of total revenue | B11: % | C11: =C7/C9 -> 0.42143565 | D11: =D7/D9 -> 0.37734547 | E11: =E7/E9 -> 0.38211414 | F11: =F7/F9 -> 0.37739198 | G11: =G7/G9 -> 0.36042403 | I11: Formula
A12: Total revenue growth YoY | B12: % | D12: =D9/C9-1 -> -0.0017224303 | E12: =E9/D9-1 -> 0.099728249 | F12: =F9/E9-1 -> 0.016669935 | G12: =G9/F9-1 -> 0.037229938 | I12: Formula
A14: PROFIT & PER SHARE
A15: Operating income (GAAP) | B15: $mm | C15: 10356 | D15: 9371 | E15: 11647 | F15: 11712 | G15: 12393 | H15: =IFERROR((G15/C15)^(1/4)-1,"") -> 0.045914303 | I15: 10-K FY2022 (SEC) p.11; 10-K FY2025 (project file) p.39
A16: Operating income (non-GAAP, company) | B16: $mm | C16: 10071 | D16: 10381 | F16: 12003 | G16: 12621 | I16: 10-K FY2022 (SEC) p.17; 10-K FY2025 (project file) p.18 (FY23 not retrieved)
A17: Operating margin (GAAP) | B17: % | C17: =C15/C9 -> 0.44593722 | D17: =D15/D9 -> 0.40421861 | E17: =E15/E9 -> 0.45683467 | F17: =F15/F9 -> 0.45185185 | G17: =G15/G9 -> 0.46096336 | I17: Formula
A18: Net income (GAAP) | B18: $mm | C18: 7545 | D18: 6177 | E18: 8469 | F18: 8223 | G18: 8563 | H18: =IFERROR((G18/C18)^(1/4)-1,"") -> 0.032147286 | I18: 10-K FY2022 (SEC) p.11; 10-K FY2025 (project file) p.39
A19: Diluted EPS (GAAP) | B19: $/sh | C19: 10.04 | D19: 8.33 | E19: 11.56 | F19: 11.39 | G19: 11.95 | H19: =IFERROR((G19/C19)^(1/4)-1,"") -> 0.04450025 | I19: 10-K FY2022 (SEC) p.11; 10-K FY2025 (project file) p.39
A20: Diluted EPS (non-GAAP, company) | B20: $/sh | C20: 9.28 | D20: 10.1 | F20: 11.72 | G20: 12.2 | I20: 10-K FY2022 (SEC) p.12; 10-K FY2025 (project file) p.13 (FY23 not retrieved)
A21: GAAP EPS growth YoY | B21: % | D21: =D19/C19-1 -> -0.17031873 | E21: =E19/D19-1 -> 0.3877551 | F21: =F19/E19-1 -> -0.014705882 | G21: =G19/F19-1 -> 0.049165935 | I21: Formula
A22: Depreciation & amortization (cash flow) | B22: $mm | C22: 1868.1 | D22: 1870.6 | E22: 1978 | F22: 2097 | G22: 2199 | H22: =IFERROR((G22/C22)^(1/4)-1,"") -> 0.041612726 | I22: 10-K FY2022 (SEC) CF stmt; 10-K FY2025 (project file) p.42
A23: EBITDA (GAAP op. income + D&A) | B23: $mm | C23: =C15+C22 -> 12224.1 | D23: =D15+D22 -> 11241.6 | E23: =E15+E22 -> 13625 | F23: =F15+F22 -> 13809 | G23: =G15+G22 -> 14592 | H23: =IFERROR((G23/C23)^(1/4)-1,"") -> 0.045260362 | I23: Formula
A25: SHARE COUNT
A26: Weighted avg diluted shares | B26: mm | C26: 751.8 | D26: 741.3 | E26: 732.3 | F26: 721.9 | G26: 716.4 | H26: =IFERROR((G26/C26)^(1/4)-1,"") -> -0.01198551 | I26: 10-K FY2022 (SEC) p.11; 10-K FY2025 (project file) p.39
A27: Shares outstanding at year end | B27: mm | C27: 745 | D27: 731 | E27: 723 | F27: 715 | G27: 711 | H27: =IFERROR((G27/C27)^(1/4)-1,"") -> -0.011610025 | I27: 10-K FY2024 (SEC) p.21 table; FY25 = 1,660.6 issued - 950.0 treasury (10-K p.41)
A28: Year-end share count change YoY | B28: % | D28: =D27/C27-1 -> -0.018791946 | E28: =E27/D27-1 -> -0.010943912 | F28: =F27/E27-1 -> -0.011065007 | G28: =G27/F27-1 -> -0.0055944056 | I28: Formula
A30: CASH FLOW & SHAREHOLDER RETURNS
A31: Cash provided by operations | B31: $mm | C31: 9141.5 | D31: 7386.6 | E31: 9612 | F31: 9447 | G31: 10551 | H31: =IFERROR((G31/C31)^(1/4)-1,"") -> 0.036499364 | I31: 10-K FY2023 Exh. 99.1 (SEC); 10-K FY2025 (project file) p.42
A32: Capital expenditures | B32: $mm | C32: 2040 | D32: 1899.2 | E32: 2357 | F32: 2775 | G32: 3365 | H32: =IFERROR((G32/C32)^(1/4)-1,"") -> 0.13328392 | I32: 10-K FY2023 Exh. 99.1 (SEC); 10-K FY2025 (project file) p.42
A33: Free cash flow (CFO - capex) | B33: $mm | C33: =C31-C32 -> 7101.5 | D33: =D31-D32 -> 5487.4 | E33: =E31-E32 -> 7255 | F33: =F31-F32 -> 6672 | G33: =G31-G32 -> 7186 | H33: =IFERROR((G33/C33)^(1/4)-1,"") -> 0.0029615416 | I33: Formula
A34: FCF conversion (FCF / net income) | B34: % | C34: =C33/C18 -> 0.94121935 | D34: =D33/D18 -> 0.88836005 | E34: =E33/E18 -> 0.85665368 | F34: =F33/F18 -> 0.81138271 | G34: =G33/G18 -> 0.83919187 | I34: Formula
A35: Capex % of revenue | B35: % | C35: =C32/C9 -> 0.087843948 | D35: =D32/D9 -> 0.081922098 | E35: =E32/E9 -> 0.0924495 | F35: =F32/F9 -> 0.10706019 | G35: =G32/G9 -> 0.12516273 | I35: Formula
A36: Dividends paid | B36: $mm | C36: 3918.6 | D36: 4168.2 | E36: 4533 | F36: 4870 | G36: 5115 | H36: =IFERROR((G36/C36)^(1/4)-1,"") -> 0.068879323 | I36: 10-K FY2022 (SEC) CF stmt; 10-K FY2025 (project file) p.42
A37: Share buybacks (treasury stock purchases, cash flow) | B37: $mm | C37: 845.5 | D37: 3896 | E37: 3054 | F37: 2824 | G37: 2056 | I37: 10-K FY2022 (SEC) CF stmt; 10-K FY2025 (project file) p.42
A38: Total returned to shareholders | B38: $mm | C38: =C36+C37 -> 4764.1 | D38: =D36+D37 -> 8064.2 | E38: =E36+E37 -> 7587 | F38: =F36+F37 -> 7694 | G38: =G36+G37 -> 7171 | I38: Formula
A39: Total returned % of FCF | B39: % | C39: =C38/C33 -> 0.67085827 | D39: =D38/D33 -> 1.4695849 | E39: =E38/E33 -> 1.0457615 | F39: =F38/F33 -> 1.1531775 | G39: =G38/G33 -> 0.99791261 | I39: Formula
A40: Dividends declared per share | B40: $/sh | C40: 5.25 | D40: 5.66 | E40: 6.23 | F40: 6.78 | G40: 7.17 | H40: =IFERROR((G40/C40)^(1/4)-1,"") -> 0.081035518 | I40: 10-K FY2024 (SEC) p.21; 10-K FY2025 (project file) p.39
A41: Dividend payout (dividends paid / net income) | B41: % | C41: =C36/C18 -> 0.51936382 | D41: =D36/D18 -> 0.67479359 | E41: =E36/E18 -> 0.53524619 | F41: =F36/F18 -> 0.59224127 | G41: =G36/G18 -> 0.59733738 | I41: Formula
A43: NET DEBT (year end)
A44: Cash & equivalents | B44: $mm | C44: 4709.2 | D44: 2583.8 | E44: 4579.3 | F44: 1085 | G44: 774 | I44: 10-K FY2022 (SEC) CF stmt; 10-K FY2025 (project file) p.41-42
A45: Total debt (incl. current maturities, excl. leases) | B45: $mm | C45: 35622.7 | D45: 35903.5 | E45: 39345.3 | F45: 38424 | G45: 39973 | I45: 10-K FY2023 Exh. 99.1 (SEC); 10-K FY2025 (project file) p.41
A46: Net debt (excl. leases) | B46: $mm | C46: =C45-C44 -> 30913.5 | D46: =D45-D44 -> 33319.7 | E46: =E45-E44 -> 34766 | F46: =F45-F44 -> 37339 | G46: =G45-G44 -> 39199 | I46: Formula
A47: Lease liabilities (current + long-term) | B47: $mm | F47: 13524 | G47: 14841 | I47: 10-K FY2025 (project file) p.41 (earlier years not retrieved)
A48: Net debt incl. leases | B48: $mm | F48: =F46+F47 -> 50863 | G48: =G46+G47 -> 54040 | I48: Formula
A49: Net debt / EBITDA (excl. leases) | B49: x | C49: =C46/C23 -> 2.5288978 | D49: =D46/D23 -> 2.9639642 | E49: =E46/E23 -> 2.551633 | F49: =F46/F23 -> 2.7039612 | G49: =G46/G23 -> 2.686335 | I49: Formula

Sheet Historical_Drivers
A1: McDonald's - historical operating drivers and GAAP-to-adjusted bridge
A2: Added after the 25-Sep feedback. All black formulas pull from Reference_Data (10-K 2025 / Q2-26 release) or Historical_5Y; blue = figure typed from the source in column H. Blank = not disclosed.
A4: Driver | B4: Unit | C4: FY2023 | D4: FY2024 | E4: FY2025 | F4: Q2 2026 | G4: H1 2026 | H4: Source / what it shows
A5: A. GROWTH DRIVERS
A6: Comparable sales - total | B6: % | C6: =Reference_Data!C69 -> 0.09 | D6: =Reference_Data!D69 -> -0.001 | E6: =Reference_Data!E69 -> 0.031 | F6: =Reference_Data!G69 -> 0.013 | G6: =Reference_Data!I69 -> 0.025 | H6: 10-K p.14 / Q2-26 release p.2. Growth has slowed from +9.0% to +3.1%, and to +1.3% in Q2-26.
A7: Comparable sales - U.S. | B7: % | C7: =Reference_Data!C70 -> 0.087 | D7: =Reference_Data!D70 -> 0.002 | E7: =Reference_Data!E70 -> 0.021 | F7: =Reference_Data!G70 -> 0.008 | G7: =Reference_Data!I70 -> 0.023 | H7: Q2-26 U.S. comps were check-led with guest counts down (release, call). Investor Day: July and August slightly negative, September expected positive, Q3 U.S. slightly negative.
A8: Comparable sales - IOM | B8: % | C8: =Reference_Data!C71 -> 0.092 | D8: =Reference_Data!D71 -> -0.002 | E8: =Reference_Data!E71 -> 0.032 | F8: =Reference_Data!G71 -> 0.015 | H8: 10-K p.14 / Q2-26 release p.2.
A9: Comparable sales - IDL | B9: % | C9: =Reference_Data!C72 -> 0.094 | D9: =Reference_Data!D72 -> -0.003 | E9: =Reference_Data!E72 -> 0.046 | F9: =Reference_Data!G72 -> 0.019 | H9: 10-K p.14 / Q2-26 release p.2.
A10: Restaurants at year end | B10: # | C10: =Reference_Data!C64+Reference_Data!C65+Reference_Data!C66 -> 41822 | D10: =Reference_Data!D64+Reference_Data!D65+Reference_Data!D66 -> 43477 | E10: =Reference_Data!E64+Reference_Data!E65+Reference_Data!E66 -> 45356 | H10: 10-K p.20 (U.S. + IOM + IDL).
A11: Net unit growth | B11: % | D11: =D10/C10-1 -> 0.039572474 | E11: =E10/D10-1 -> 0.043218253 | H11: Investor Day: net unit growth of nearly 4.5% in 2027, easing to 3-3.5% a year in 2028-30.
A12: Gross restaurant openings | B12: # | D12: =Reference_Data!D75 -> 2116 | E12: =Reference_Data!E75 -> 2276 | H12: 10-K p.20.
A13: Franchised sales | B13: $mm | C13: =SUM(Reference_Data!C53:C55) -> 119751 | D13: =SUM(Reference_Data!D53:D55) -> 120933 | E13: =SUM(Reference_Data!E53:E55) -> 129675 | H13: 10-K p.15 (U.S. + IOM + IDL). Not revenue: the base on which rent and royalties are charged.
A14: Company-operated sales | B14: $mm | C14: =Reference_Data!C11 -> 9742 | D14: =Reference_Data!D11 -> 9782 | E14: =Reference_Data!E11 -> 9690 | H14: 10-K p.39.
A15: Systemwide sales | B15: $bn | C15: =(C13+C14)/1000 -> 129.493 | D15: =(D13+D14)/1000 -> 130.715 | E15: =(E13+E14)/1000 -> 139.365 | H15: Franchised + company-operated sales; FY25 ties to the reported $139.4bn (10-K p.8).
A16: Systemwide sales growth (reported US$) | B16: % | D16: =D15/C15-1 -> 0.0094368035 | E16: =E15/D15-1 -> 0.066174502 | H16: Includes FX; constant-currency growth was 2% (FY24) and 5% (FY25) per 10-K p.14.
A18: B. HOW SALES TURN INTO REVENUE AND MARGIN
A19: Take rate - total (franchised revenue / franchised sales) | B19: % | C19: =Reference_Data!C10/C13 -> 0.12890915 | D19: =Reference_Data!D10/D13 -> 0.12994799 | E19: =Reference_Data!E10/E13 -> 0.12761134 | H19: Cents of revenue per $1 of franchisee sales: stable at ~13%, so revenue tracks systemwide sales.
A20: Take rate - U.S. (rent + royalty) | B20: % | C20: =Reference_Data!C47/Reference_Data!C53 -> 0.14350683 | D20: =Reference_Data!D47/Reference_Data!D53 -> 0.14343969 | E20: =Reference_Data!E47/Reference_Data!E53 -> 0.14189735 | H20: ~14 cents per U.S. franchised sales dollar (not per total U.S. sales dollar).
A21: Take rate - IOM (rent + royalty) | B21: % | C21: =Reference_Data!C48/Reference_Data!C54 -> 0.17115304 | D21: =Reference_Data!D48/Reference_Data!D54 -> 0.17239088 | E21: =Reference_Data!E48/Reference_Data!E54 -> 0.17151272 | H21: Conventional franchise, McDonald's owns or leases the real estate.
A22: Take rate - IDL (royalty only) | B22: % | C22: =Reference_Data!C49/Reference_Data!C55 -> 0.054603617 | D22: =Reference_Data!D49/Reference_Data!D55 -> 0.055758191 | E22: =Reference_Data!E49/Reference_Data!E55 -> 0.053784465 | H22: IDL & Corporate franchised revenue / IDL franchised sales. Licensee owns the real estate, so new IDL units add little revenue.
A23: Franchised margin % | B23: % | C23: =(Reference_Data!C10-Reference_Data!C14)/Reference_Data!C10 -> 0.83967092 | D23: =(Reference_Data!D10-Reference_Data!D14)/Reference_Data!D10 -> 0.83862552 | E23: =(Reference_Data!E10-Reference_Data!E14)/Reference_Data!E10 -> 0.84179357 | H23: Franchised revenue less occupancy costs: ~84% and steady.
A24: Company-operated margin % | B24: % | C24: =(Reference_Data!C11-Reference_Data!C15)/Reference_Data!C11 -> 0.15582016 | D24: =(Reference_Data!D11-Reference_Data!D15)/Reference_Data!D11 -> 0.14802699 | E24: =(Reference_Data!E11-Reference_Data!E15)/Reference_Data!E11 -> 0.14664603 | H24: Falling: food, paper and labour inflation.
A25: Company-operated margin % - U.S. | B25: % | C25: =Reference_Data!C59/Reference_Data!C50 -> 0.15150574 | D25: =Reference_Data!D59/Reference_Data!D50 -> 0.13043478 | E25: =Reference_Data!E59/Reference_Data!E50 -> 0.11556982 | H25: 15.2% -> 11.6%: the main reason refranchising lifts group margin.
A26: SG&A % of systemwide sales | B26: % | C26: =(Reference_Data!C17+Reference_Data!C18)/(C15*1000) -> 0.021754072 | D26: =(Reference_Data!D17+Reference_Data!D18)/(D15*1000) -> 0.021872012 | E26: =(Reference_Data!E17+Reference_Data!E18)/(E15*1000) -> 0.021813224 | H26: Flat at ~2.2%; target ~1.9% by 2030 (Investor Day), decline starting 2027.
A27: Operating margin (GAAP) | B27: % | C27: =Reference_Data!C31/Reference_Data!C13 -> 0.45683467 | D27: =Reference_Data!D31/Reference_Data!D13 -> 0.45185185 | E27: =Reference_Data!E31/Reference_Data!E13 -> 0.46096336 | F27: =Reference_Data!G31/Reference_Data!G13 -> 0.47014085 | G27: =Reference_Data!I31/Reference_Data!I13 -> 0.46210341 | H27: 10-K p.39 / Q2-26 release.
A28: Operating margin (adjusted: before special charges) | B28: % | D28: =IF(Reference_Data!D40="","",(Reference_Data!D31+Reference_Data!D40)/Reference_Data!D13) -> 0.4630787 | E28: =IF(Reference_Data!E40="","",(Reference_Data!E31+Reference_Data!E40)/Reference_Data!E13) -> 0.46948112 | F28: =IF(Reference_Data!G40="","",(Reference_Data!G31+Reference_Data!G40)/Reference_Data!G13) -> 0.47746479 | G28: =IF(Reference_Data!I40="","",(Reference_Data!I31+Reference_Data!I40)/Reference_Data!I13) -> 0.46937427 | H28: FY23 special charges are not given in the 2025 10-K. H1-26 46.9% matches the release.
A30: C. CASH, RETURNS AND LEVERAGE
A31: Capital expenditures | B31: $mm | C31: =Reference_Data!C82 -> 2357 | D31: =Reference_Data!D82 -> 2775 | E31: =Reference_Data!E82 -> 3365 | H31: 10-K p.42.
A32: Capex % of revenue | B32: % | C32: =C31/Reference_Data!C13 -> 0.0924495 | D32: =D31/Reference_Data!D13 -> 0.10706019 | E32: =E31/Reference_Data!E13 -> 0.12516273 | H32: Rising with record unit openings; NEXT adds $8.5bn of partnering to 2036 (~$5bn by 2030).
A33: Free cash flow (CFO - capex, company definition) | B33: $mm | C33: =Reference_Data!C81-Reference_Data!C82 -> 7255 | D33: =Reference_Data!D81-Reference_Data!D82 -> 6672 | E33: =Reference_Data!E81-Reference_Data!E82 -> 7186 | H33: 10-K p.42. This is the company FCF, not the UFCF used in the DCF.
A34: FCF conversion (FCF / GAAP net income, company definition) | B34: % | C34: =C33/Reference_Data!C32 -> 0.85665368 | D34: =D33/Reference_Data!D32 -> 0.81138271 | E34: =E33/Reference_Data!E32 -> 0.83919187 | H34: 10-K p.30 reports 84% (2025) and 81% (2024); guidance low-to-mid 80% for 2026.
A35: After-tax ROIC (company-reported, continuing operations) | B35: % | C35: 0.252 | D35: 0.218 | E35: 0.203 | H35: 2025 Annual Report p.30 (10-K MD&A; reconciliation in Exhibit 99.1). Falling as investment rises ahead of returns.
A36: Dividends + buybacks | B36: $mm | C36: =Reference_Data!C84+Reference_Data!C85 -> 7587 | D36: =Reference_Data!D84+Reference_Data!D85 -> 7694 | E36: =Reference_Data!E84+Reference_Data!E85 -> 7171 | H36: 10-K p.42.
A37: Net debt / EBITDA (excl. leases) | B37: x | C37: =Historical_5Y!E49 -> 2.551633 | D37: =Historical_5Y!F49 -> 2.7039612 | E37: =Historical_5Y!G49 -> 2.686335 | H37: Historical_5Y tab. Steady ~2.6-2.7x.
A38: EBIT / interest expense (GAAP) | B38: x | C38: =Reference_Data!C31/Reference_Data!C22 -> 8.5576782 | D38: =Reference_Data!D31/Reference_Data!D22 -> 7.7768924 | E38: =Reference_Data!E31/Reference_Data!E22 -> 7.8337547 | F38: =Reference_Data!G31/Reference_Data!G22 -> 8.1613692 | G38: =Reference_Data!I31/Reference_Data!I22 -> 7.7775031 | H38: Coverage has eased from 8.6x as interest costs rose; still comfortable.
A40: D. GAAP TO ADJUSTED BRIDGE (restructuring and other special charges)
A41: Bridge | B41: Unit | C41: FY2024 | D41: FY2025 | E41: H1 2025 | F41: H1 2026 | H41: Note
A42: Operating income (GAAP) | B42: $mm | C42: =Reference_Data!D31 -> 11712 | D42: =Reference_Data!E31 -> 12393 | E42: =Reference_Data!H31 -> 5880 | F42: =Reference_Data!I31 -> 6292 | H42: 10-K p.39 / Q2-26 release.
A43: Add: special charges, pre-tax (mainly restructuring) | B43: $mm | C43: =Reference_Data!D40 -> 291 | D43: =Reference_Data!E40 -> 229 | E43: =Reference_Data!H40 -> 109 | F43: =Reference_Data!I40 -> 99 | H43: 10-K p.13, 18 / Q2-26 release p.2. Charges recurred every year 2023-26 ($795m cumulative since the programme began; completes 2027).
A44: Operating income (adjusted) | B44: $mm | C44: =C42+C43 -> 12003 | D44: =D42+D43 -> 12622 | E44: =E42+E43 -> 5989 | F44: =F42+F43 -> 6391
A45: Reported non-GAAP operating income (check) | B45: $mm | C45: =Historical_5Y!F16 -> 12003 | D45: =Historical_5Y!G16 -> 12621 | H45: Historical_5Y row 16.
A46: Difference (rounding) | B46: $mm | C46: =C44-C45 -> 0 | D46: =D44-D45 -> 1
A47: Diluted EPS (GAAP) | B47: $/sh | C47: =Reference_Data!D33 -> 11.39 | D47: =Reference_Data!E33 -> 11.95 | E47: =Reference_Data!H33 -> 5.74 | F47: =Reference_Data!I33 -> 6.1
A48: Add: after-tax special charges per diluted share | B48: $/sh | C48: =Reference_Data!D41/Reference_Data!D27 -> 0.32691509 | D48: =Reference_Data!E41/Reference_Data!E27 -> 0.24846454 | E48: =Reference_Data!H41/Reference_Data!H27 -> 0.11700794 | F48: =Reference_Data!I41/Reference_Data!I27 -> 0.10669662 | H48: After-tax charges / weighted diluted shares.
A49: Diluted EPS (adjusted) | B49: $/sh | C49: =C47+C48 -> 11.716915 | D49: =D47+D48 -> 12.198465 | E49: =E47+E48 -> 5.8570079 | F49: =F47+F48 -> 6.2066966
A50: Reported adjusted EPS (check) | B50: $/sh | C50: =Historical_5Y!F20 -> 11.72 | D50: =Historical_5Y!G20 -> 12.2 | F50: 6.21 | H50: Historical_5Y row 20; H1-26 $6.21 typed from the Q2-26 release p.3 (blue).
A51: Difference (rounding) | B51: $/sh | C51: =C49-C50 -> -0.0030849148 | D51: =D49-D50 -> -0.0015354551 | F51: =F49-F50 -> -0.0033033834
A53: WHAT THE HISTORY SAYS
A54: 1. Growth has slowed and turned check-led: global comps +9.0% (FY23) -> +3.1% (FY25) -> +1.3% in Q2-26; U.S. +0.8% in Q2-26 with guest counts down.
A55: 2. The rent/royalty engine is intact: take rate ~13% and franchised margin ~84% barely moved, so revenue tracks systemwide sales. The weak spot is U.S. company-operated margin (15.2% -> 11.6%).
A56: 3. Returns are falling as investment rises: after-tax ROIC 25.2% -> 20.3% while capex rose from 9.2% to 12.5% of revenue. NEXT (5-6 year payback for McDonald's) makes a quick ROIC recovery unlikely.
A57: 4. Cash conversion and leverage are steady: FCF conversion 81-86%, net debt / EBITDA ~2.6-2.7x, EBIT covers interest ~8x.

Sheet Industry_Evidence
A1: Independent industry evidence and franchisee unit economics
A2: Added after the 25-Sep feedback (the report leaned on management framing). Blue = figure typed from the source in column E. Not linked into the valuation; used to test the traffic and franchisee assumptions.
A4: Measure | B4: Value | C4: Unit | D4: Period | E4: Source | F4: Why it matters for MCD
A5: INDUSTRY TRAFFIC - independent of McDonald's
A6: U.S. quick-service net sales growth | B6: 0.013 | C6: % | D6: Q4 2025 | E6: Revenue Management Solutions, via ClearCOGS H1-2026 demand review (compiles RMS, Black Box, NRA, BLS): clearcogs.com/blog/restaurant-demand-outlook-h2-2026 (1-Jul-2026) | F6: Industry growth is check-led, the same mechanism as MCD in Q2-26.
A7: U.S. quick-service traffic growth | B7: -0.02 | C7: % | D7: Q4 2025 | E7: Revenue Management Solutions, via ClearCOGS (above) | F7: Visits falling across the category, not only at MCD.
A8: U.S. quick-service average check growth | B8: 0.033 | C8: % | D8: Q4 2025 | E8: Revenue Management Solutions, via ClearCOGS (above) | F8: Price/mix doing the work; limits how long check can offset traffic.
A9: Restaurant same-store sales growth | B9: 0.01 | C9: % | D9: Jan 2026 | E9: Black Box Intelligence, via ClearCOGS (above) | F9: Traffic -1.1% in the same month.
A10: Restaurant traffic growth | B10: -0.02 | C10: % | D10: Feb 2026 | E10: Black Box Intelligence, via ClearCOGS (above) | F10: Same-store sales +1.6% in the same month.
A11: Operators reporting lower traffic y/y | B11: 0.45 | C11: % | D11: May 2026 | E11: National Restaurant Association survey, via ClearCOGS (above) | F11: 15th net traffic decline in 16 months.
A12: Food-away-from-home CPI (12 months) | B12: 0.035 | C12: % | D12: to May 2026 | E12: U.S. BLS, via ClearCOGS (above) | F12: Food at home +2.7%: eating out keeps getting relatively dearer, pushing visits to grocery.
A13: Industry traffic growth forecast | B13: 0.01 | C13: % (max) | D13: 2026 | E13: Circana (D. Portalatin), via Restaurant Dive, 8-Jan-2026: restaurantdive.com/news/six-restaurant-trends-2026-outlook/809073 | F13: "Less than 1%": consistent with management's flat-industry-traffic assumption; growth must come from share.
A14: QSR visits vs H1-2026 weekly average | B14: 0.016 | C14: % | D14: 24-30 Aug 2026 | E14: Placer.ai, via Fast Casual: fastcasual.com/news/restaurant-traffic-moderates-in-late-august-fast-casual-chains-still-outperform | F14: Late-summer QSR traffic held up; a stabilisation signal, not a recovery.
A15: McDonald's visits vs its own H1-2026 weekly average | B15: 0.03 | C15: % | D15: 24-30 Aug 2026 | E15: Placer.ai, via Fast Casual (above) | F15: Chick-fil-A +9.8% the same week: the value and chicken competition MCD is targeting.
A16: McDONALD'S FRANCHISEE UNIT ECONOMICS - company-disclosed at Investor Day (23-Sep-2026)
A17: U.S. average unit volume (more than) | B17: 4 | C17: $m | D17: 2026 | E17: Investor Day transcript (CFO) | F17: The base rent and royalties are charged on.
A18: U.S. franchisee operating cash flow per restaurant (about) | B18: 0.5 | C18: $m | D18: 2026 | E18: Investor Day transcript (CFO) | F18: Cash-flow margin ~12.5% of sales (row below): the buffer that funds remodels and NEXT.
A19: Implied U.S. franchisee cash-flow margin | B19: =B18/B17 -> 0.125 | C19: % | D19: 2026 | E19: Formula | F19: Thin enough that sustained traffic declines would erode it quickly.
A20: U.S. franchisee total cash flow vs 2019 | B20: 0.5 | C20: % | D20: 2026 vs 2019 | E20: Investor Day transcript (CFO) | F20: "Nearly 50%" higher: franchisees start NEXT from a strong position.
A21: Big-5 IOM average unit volume (more than) | B21: 4.5 | C21: $m | D21: 2026 | E21: Investor Day transcript (CFO) | F21: Cash flow ~$0.4m per restaurant (~9% margin).
A22: NEXT payback for McDonald's (years) | B22: 5.5 | C22: years | D22: 2027-36 | E22: Investor Day transcript (CFO) | F22: 5-6 years (franchisees ~4 years after partnering): supports the ROIC decline in Historical_Drivers row 35.
A23: U.S. comparable sales guide for Q3 2026 | B23: slightly negative | C23: text | D23: Q3 2026 | E23: Investor Day transcript (Q&A) | F23: July and August slightly negative, September expected positive: the bar for the Q3 catalyst.

Sheet Reference_Data
A1: Reference Data - figures extracted from the filings (do not edit)
A2: Values found in the 10-K, Q2 2026 release and call, with page references. Feeds Historical_Drivers, Comps and Forecast.
A4: Line item | B4: Unit | C4: FY2023 | D4: FY2024 | E4: FY2025 | F4: Q2 2025 | G4: Q2 2026 | H4: H1 2025 | I4: H1 2026 | J4: Source (document, page)
A6: 1. INCOME STATEMENT
A7: Rents (franchised) | B7: $mm | C7: 9840 | D7: 10017 | E7: 10442 | J7: 10-K 2025 p.53 Franchise Arrangements
A8: Royalties (franchised) | B8: $mm | C8: 5531 | D8: 5606 | E8: 6018 | J8: 10-K 2025 p.53
A9: Initial fees (franchised) | B9: $mm | C9: 66 | D9: 92 | E9: 88 | J9: 10-K 2025 p.53
A10: Revenues from franchised restaurants | B10: $mm | C10: 15437 | D10: 15715 | E10: 16548 | F10: 4213 | G10: 4393 | H10: 7874 | I10: 8399 | J10: 10-K 2025 p.39 / Q2 26 release p.5-6
A11: Sales by Company-owned & operated restaurants | B11: $mm | C11: 9742 | D11: 9782 | E11: 9690 | F11: 2458 | G11: 2525 | H11: 4590 | I11: 4842 | J11: 10-K 2025 p.39 / Q2 26 release p.5-6
A12: Other revenues | B12: $mm | C12: 316 | D12: 423 | E12: 647 | F12: 172 | G12: 182 | H12: 334 | I12: 375 | J12: 10-K 2025 p.39 / Q2 26 release p.5-6
A13: Total revenues | B13: $mm | C13: =IF(COUNT(C10,C11,C12)<3,"",C10+C11+C12) -> 25495 | D13: =IF(COUNT(D10,D11,D12)<3,"",D10+D11+D12) -> 25920 | E13: =IF(COUNT(E10,E11,E12)<3,"",E10+E11+E12) -> 26885 | F13: =IF(COUNT(F10,F11,F12)<3,"",F10+F11+F12) -> 6843 | G13: =IF(COUNT(G10,G11,G12)<3,"",G10+G11+G12) -> 7100 | H13: =IF(COUNT(H10,H11,H12)<3,"",H10+H11+H12) -> 12798 | I13: =IF(COUNT(I10,I11,I12)<3,"",I10+I11+I12) -> 13616
A14: Franchised restaurants - occupancy expenses | B14: $mm | C14: 2475 | D14: 2536 | E14: 2618 | F14: 654 | G14: 680 | H14: 1274 | I14: 1356 | J14: 10-K 2025 p.39 / Q2 26 release p.5-6
A15: Company-operated restaurant expenses (total) | B15: $mm | C15: 8224 | D15: 8334 | E15: 8269 | F15: 2078 | G15: 2138 | H15: 3937 | I15: 4170 | J15: 10-K 2025 p.39 (sum of 3 lines) / Q2 26 release
A16: Other restaurant expenses | B16: $mm | C16: 232 | D16: 339 | E16: 564 | F16: 149 | G16: 163 | H16: 289 | I16: 329 | J16: 10-K 2025 p.39 / Q2 26 release
A17: SG&A - depreciation & amortization | B17: $mm | C17: 382 | D17: 447 | E17: 457 | F17: 106 | G17: 111 | H17: 213 | I17: 222 | J17: 10-K 2025 p.39 / Q2 26 release
A18: SG&A - other | B18: $mm | C18: 2435 | D18: 2412 | E18: 2583 | F18: 595 | G18: 706 | H18: 1170 | I18: 1354 | J18: 10-K 2025 p.39 / Q2 26 release
A19: Other operating (income) expense, net | B19: $mm | C19: 99 | D19: 139 | E19: 2 | F19: 29 | G19: -37 | H19: 36 | I19: -106 | J19: 10-K 2025 p.39 / Q2 26 release
A20: Total operating costs & expenses | B20: $mm | C20: =IF(COUNT(C14,C15,C16,C17,C18,C19)<6,"",SUM(C14,C15,C16,C17,C18,C19)) -> 13847 | D20: =IF(COUNT(D14,D15,D16,D17,D18,D19)<6,"",SUM(D14,D15,D16,D17,D18,D19)) -> 14207 | E20: =IF(COUNT(E14,E15,E16,E17,E18,E19)<6,"",SUM(E14,E15,E16,E17,E18,E19)) -> 14493 | F20: =IF(COUNT(F14,F15,F16,F17,F18,F19)<6,"",SUM(F14,F15,F16,F17,F18,F19)) -> 3611 | G20: =IF(COUNT(G14,G15,G16,G17,G18,G19)<6,"",SUM(G14,G15,G16,G17,G18,G19)) -> 3761 | H20: =IF(COUNT(H14,H15,H16,H17,H18,H19)<6,"",SUM(H14,H15,H16,H17,H18,H19)) -> 6919 | I20: =IF(COUNT(I14,I15,I16,I17,I18,I19)<6,"",SUM(I14,I15,I16,I17,I18,I19)) -> 7325
A21: Operating income (calculated) | B21: $mm | C21: =IF(OR(C13="",C20=""),"",C13-C20) -> 11648 | D21: =IF(OR(D13="",D20=""),"",D13-D20) -> 11713 | E21: =IF(OR(E13="",E20=""),"",E13-E20) -> 12392 | F21: =IF(OR(F13="",F20=""),"",F13-F20) -> 3232 | G21: =IF(OR(G13="",G20=""),"",G13-G20) -> 3339 | H21: =IF(OR(H13="",H20=""),"",H13-H20) -> 5879 | I21: =IF(OR(I13="",I20=""),"",I13-I20) -> 6291
A22: Interest expense | B22: $mm | C22: 1361 | D22: 1506 | E22: 1582 | F22: 390 | G22: 409 | H22: 766 | I22: 809 | J22: 10-K 2025 p.39 / Q2 26 release
A23: Nonoperating (income) expense, net | B23: $mm | C23: -236 | D23: -139 | E23: -87 | F23: -18 | G23: -6 | H23: -76 | I23: 5 | J23: 10-K 2025 p.39 / Q2 26 release
A24: Income before taxes | B24: $mm | C24: =IF(OR(C21="",COUNT(C22,C23)<2),"",C21-C22-C23) -> 10523 | D24: =IF(OR(D21="",COUNT(D22,D23)<2),"",D21-D22-D23) -> 10346 | E24: =IF(OR(E21="",COUNT(E22,E23)<2),"",E21-E22-E23) -> 10897 | F24: =IF(OR(F21="",COUNT(F22,F23)<2),"",F21-F22-F23) -> 2860 | G24: =IF(OR(G21="",COUNT(G22,G23)<2),"",G21-G22-G23) -> 2936 | H24: =IF(OR(H21="",COUNT(H22,H23)<2),"",H21-H22-H23) -> 5189 | I24: =IF(OR(I21="",COUNT(I22,I23)<2),"",I21-I22-I23) -> 5477
A25: Provision for income taxes | B25: $mm | C25: 2053 | D25: 2121 | E25: 2334 | F25: 608 | G25: 574 | H25: 1069 | I25: 1133 | J25: 10-K 2025 p.39 / Q2 26 release
A26: Net income (calculated) | B26: $mm | C26: =IF(OR(C24="",C25=""),"",C24-C25) -> 8470 | D26: =IF(OR(D24="",D25=""),"",D24-D25) -> 8225 | E26: =IF(OR(E24="",E25=""),"",E24-E25) -> 8563 | F26: =IF(OR(F24="",F25=""),"",F24-F25) -> 2252 | G26: =IF(OR(G24="",G25=""),"",G24-G25) -> 2362 | H26: =IF(OR(H24="",H25=""),"",H24-H25) -> 4120 | I26: =IF(OR(I24="",I25=""),"",I24-I25) -> 4344
A27: Weighted avg diluted shares | B27: mm | C27: 732.3 | D27: 721.9 | E27: 716.4 | F27: 717.6 | G27: 711.1 | H27: 717.9 | I27: 712.3 | J27: 10-K 2025 p.39 / Q2 26 release
A28: Diluted EPS (calculated) | B28: $/sh | C28: =IF(OR(C26="",N(C27)=0),"",C26/C27) -> 11.566298 | D28: =IF(OR(D26="",N(D27)=0),"",D26/D27) -> 11.393545 | E28: =IF(OR(E26="",N(E27)=0),"",E26/E27) -> 11.95282 | F28: =IF(OR(F26="",N(F27)=0),"",F26/F27) -> 3.1382386 | G28: =IF(OR(G26="",N(G27)=0),"",G26/G27) -> 3.3216144 | H28: =IF(OR(H26="",N(H27)=0),"",H26/H27) -> 5.7389609 | I28: =IF(OR(I26="",N(I27)=0),"",I26/I27) -> 6.098554
A30: 2. TIE-OUT TO REPORTED FIGURES
A31: Reported operating income | B31: $mm | C31: 11647 | D31: 11712 | E31: 12393 | F31: 3232 | G31: 3338 | H31: 5880 | I31: 6292 | J31: 10-K 2025 p.39 / Q2 26 release
A32: Reported net income | B32: $mm | C32: 8469 | D32: 8223 | E32: 8563 | F32: 2253 | G32: 2362 | H32: 4121 | I32: 4345 | J32: 10-K 2025 p.39 / Q2 26 release
A33: Reported diluted EPS | B33: $/sh | C33: 11.56 | D33: 11.39 | E33: 11.95 | F33: 3.14 | G33: 3.32 | H33: 5.74 | I33: 6.1 | J33: 10-K 2025 p.39 / Q2 26 release
A34: Tie-out: calc - reported operating income | B34: $mm | C34: =IF(OR(C21="",C31=""),"",C21-C31) -> 1 | D34: =IF(OR(D21="",D31=""),"",D21-D31) -> 1 | E34: =IF(OR(E21="",E31=""),"",E21-E31) -> -1 | F34: =IF(OR(F21="",F31=""),"",F21-F31) -> 0 | G34: =IF(OR(G21="",G31=""),"",G21-G31) -> 1 | H34: =IF(OR(H21="",H31=""),"",H21-H31) -> -1 | I34: =IF(OR(I21="",I31=""),"",I21-I31) -> -1 | J34: Should be ~0 (±2 from rounding)
A35: Tie-out: calc - reported net income | B35: $mm | C35: =IF(OR(C26="",C32=""),"",C26-C32) -> 1 | D35: =IF(OR(D26="",D32=""),"",D26-D32) -> 2 | E35: =IF(OR(E26="",E32=""),"",E26-E32) -> 0 | F35: =IF(OR(F26="",F32=""),"",F26-F32) -> -1 | G35: =IF(OR(G26="",G32=""),"",G26-G32) -> 0 | H35: =IF(OR(H26="",H32=""),"",H26-H32) -> -1 | I35: =IF(OR(I26="",I32=""),"",I26-I32) -> -1 | J35: Should be ~0 (±2 from rounding)
A36: Tie-out: rents+royalties+fees - franchised revenue | B36: $mm | C36: =IF(COUNT(C7,C8,C9,C10)<4,"",C7+C8+C9-C10) -> 0 | D36: =IF(COUNT(D7,D8,D9,D10)<4,"",D7+D8+D9-D10) -> 0 | E36: =IF(COUNT(E7,E8,E9,E10)<4,"",E7+E8+E9-E10) -> 0 | J36: Should be 0
A38: 3. PER SHARE, SPECIAL ITEMS & COST MEMO
A39: Dividends declared per share | B39: $/sh | C39: 6.23 | D39: 6.78 | E39: 7.17 | J39: 10-K 2025 p.39
A40: Special charges, pre-tax (mainly restructuring) | B40: $mm | D40: 291 | E40: 229 | F40: 43 | G40: 52 | H40: 109 | I40: 99 | J40: 10-K 2025 p.13, 18 / Q2 26 release p.2
A41: Special charges, after tax | B41: $mm | D41: 236 | E41: 178 | F41: 34 | G41: 40 | H41: 84 | I41: 76 | J41: 10-K 2025 p.13 / Q2 26 release p.3
A42: Memo: Food & paper (company-op) | B42: $mm | C42: 3039 | D42: 2995 | E42: 3006 | J42: 10-K 2025 p.39
A43: Memo: Payroll & employee benefits (company-op) | B43: $mm | C43: 2886 | D43: 2959 | E43: 2905 | J43: 10-K 2025 p.39
A44: Memo: Occupancy & other (company-op) | B44: $mm | C44: 2299 | D44: 2381 | E44: 2358 | J44: 10-K 2025 p.39
A46: 4. SEGMENT DATA (annual only - not in the Q2 release)
A47: Franchised revenues - U.S. | B47: $mm | C47: 7163 | D47: 7211 | E47: 7371 | J47: 10-K 2025 p.14
A48: Franchised revenues - IOM | B48: $mm | C48: 6549 | D48: 6746 | E48: 7279 | J48: 10-K 2025 p.14
A49: Franchised revenues - IDL & Corporate | B49: $mm | C49: 1724 | D49: 1758 | E49: 1898 | J49: 10-K 2025 p.14
A50: Company-op sales - U.S. | B50: $mm | C50: 3221 | D50: 3197 | E50: 3115 | J50: 10-K 2025 p.14
A51: Company-op sales - IOM | B51: $mm | C51: 5702 | D51: 5713 | E51: 6131 | J51: 10-K 2025 p.14
A52: Company-op sales - IDL & Corporate | B52: $mm | C52: 819 | D52: 872 | E52: 443 | J52: 10-K 2025 p.14
A53: Franchised sales (not revenue) - U.S. | B53: $mm | C53: 49914 | D53: 50272 | E53: 51946 | J53: 10-K 2025 p.15
A54: Franchised sales - IOM | B54: $mm | C54: 38264 | D54: 39132 | E54: 42440 | J54: 10-K 2025 p.15
A55: Franchised sales - IDL | B55: $mm | C55: 31573 | D55: 31529 | E55: 35289 | J55: 10-K 2025 p.15
A56: Franchised margin - U.S. | B56: $mm | C56: 5877 | D56: 5916 | E56: 6078 | J56: 10-K 2025 p.15
A57: Franchised margin - IOM | B57: $mm | C57: 5379 | D57: 5514 | E57: 5954 | J57: 10-K 2025 p.15
A58: Franchised margin - IDL & Corporate | B58: $mm | C58: 1706 | D58: 1748 | E58: 1897 | J58: 10-K 2025 p.15
... A66: Restaurants at period end - IDL | B66: # | C66: 18102 | D66: 19408 | E66: 20805 | J66: 10-K 2025 p.20
A68: 5. OPERATING KPIs
A69: Comparable sales - Total | B69: % | C69: 0.09 | D69: -0.001 | E69: 0.031 | F69: 0.038 | G69: 0.013 | I69: 0.025 | J69: 10-K 2025 p.14 / Q2 26 release p.2 / Q2 26 call
A70: Comparable sales - U.S. | B70: % | C70: 0.087 | D70: 0.002 | E70: 0.021 | F70: 0.025 | G70: 0.008 | I70: 0.023 | J70: 10-K 2025 p.14 / Q2 26 release p.2 / Q2 26 call
A71: Comparable sales - IOM | B71: % | C71: 0.092 | D71: -0.002 | E71: 0.032 | F71: 0.04 | G71: 0.015 | J71: 10-K 2025 p.14 / Q2 26 release p.2
A72: Comparable sales - IDL | B72: % | C72: 0.094 | D72: -0.003 | E72: 0.046 | F72: 0.056 | G72: 0.019 | J72: 10-K 2025 p.14 / Q2 26 release p.2
A73: Systemwide sales | B73: $bn | E73: 139.4 | G73: 37 | J73: 10-K 2025 p.8 / Q2 26 release p.1 (Q2 rounded)
A74: Systemwide sales growth, constant currency | B74: % | D74: 0.02 | E74: 0.05 | G74: 0.04 | I74: 0.05 | J74: 10-K 2025 p.14 / Q2 26 release p.1 / Q2 26 call
A75: Gross restaurant openings | B75: # | D75: 2116 | E75: 2276 | J75: 10-K 2025 p.20
A76: Restaurant closures | B76: # | D76: 461 | E76: 396 | J76: 10-K 2025 p.20
A77: 90-day active loyalty users (approx.) | B77: mm | E77: 210 | G77: 220 | I77: 220 | J77: Shareholder letter / Q2 26 release p.1
A78: Systemwide sales to loyalty members, TTM | B78: $bn | G78: 40 | I78: 40 | J78: Q2 26 release p.1
A80: 6. CASH FLOW
A81: Cash provided by operations | B81: $mm | C81: 9612 | D81: 9447 | E81: 10551 | J81: 10-K 2025 p.42
A82: Capital expenditures | B82: $mm | C82: 2357 | D82: 2775 | E82: 3365 | J82: 10-K 2025 p.42 (enter as positive)
A83: Depreciation & amortization (cash flow) | B83: $mm | C83: 1978 | D83: 2097 | E83: 2199 | J83: 10-K 2025 p.42
A84: Treasury stock purchases (buybacks) | B84: $mm | C84: 3054 | D84: 2824 | E84: 2056 | J84: 10-K 2025 p.42 (enter as positive)
A85: Common stock dividends paid | B85: $mm | C85: 4533 | D85: 4870 | E85: 5115 | J85: 10-K 2025 p.42 (enter as positive)
A87: 7. BALANCE SHEET (year-end)
A88: Cash & equivalents | B88: $mm | D88: 1085 | E88: 774 | J88: 10-K 2025 p.41
A89: Long-term debt | B89: $mm | D89: 38424 | E89: 39973 | J89: 10-K 2025 p.41
A90: Lease liability - current | B90: $mm | D90: 636 | E90: 694 | J90: 10-K 2025 p.41
A91: Lease liability - long-term | B91: $mm | D91: 12888 | E91: 14147 | J91: 10-K 2025 p.41
A92: Total shareholders' equity (deficit) | B92: $mm | D92: -3797 | E92: -1791 | J92: 10-K 2025 p.41
A94: 8. MARKET DATA (single values - column C)
A95: Share price ($) | J95: User: enter latest price
A96: Price date | J96: User
A97: Shares outstanding (mm) | C97: 710.4 | J97: 10-K 2025 cover: 710,398,642 at 31-Jan-2026
A98: Annualized dividend per share ($) | C98: 7.44 | J98: 10-K 2025 p.8: Q4-25 dividend $1.86 x 4

Sheet Model_Review
A1: Model review against the valuation guides (IBIG Module 4: EV & Multiples; Valuation & DCF)
A2: Each row: the guide principle, what the model did, what was changed. Value impacts are approximate, one change at a time in this order.
A4: # | B4: Area | C4: Guide principle (source) | D4: Before the review | E4: Change made / status | F4: Status
A5: 1 | B5: DCF - terminal growth | C5: Terminal growth 1-3% in developed markets, in line with inflation, below GDP; UFCF growth should converge to it (DCF Key Rule #6). | D5: 3.0% - at the ceiling of the range; FY30 UFCF growth 7.1%, so a big jump down into the terminal period. | E5: Base g lowered to 2.5%; 1.5-3.5% shown in the grid. | F5: Changed
A6: 2 | B6: DCF - normalised terminal year | C6: If final-year FCF growth differs a lot from terminal growth, or capex will change later, build a normalised terminal year (DCF Key Rule #11). | D6: Terminal FCF = FY30 UFCF x (1+g); capex fixed at $3.45bn so capex % fell to 11.3%. | E6: Terminal-year FCF rebuilt from FY31 revenue with FY30 margin and FY27-30 average capex %. Checks added on DCF tab. | F6: Changed
A7: 3 | B7: Forecast - margin stabilisation | C7: Margins should stabilise by the end of the explicit forecast (DCF Key Rule #4). | D7: Margin still +0.7pp in FY30. | E7: Ramp 47.0 / 49.5 / 51.5 / 52.5 / 53.0%; final step 0.5pp. 2030 end point unchanged. | F7: Changed
A8: 4 | B8: Forecast - non-recurring items | C8: Only add back charges that are truly non-recurring (e.g. once in 10 years) (DCF Key Rule #8; Multiples Key Rule #4). | D8: FCF built on adjusted operating income - restructuring excluded although it recurred every year 2023-26. | E8: Restructuring deducted as a cash cost: $250m FY26 (10-Q guidance), $100m FY27, then nil. Adjusted EPS kept only for P/E (matches consensus). | F8: Changed
A9: 5 | B9: DCF - stock-based comp | C9: SBC is a real cost and must not be added back to UFCF (DCF Key Rule #2). | D9: Not added back, but the "other cash items" line was sized on CFO - NI - D&A history, which includes an SBC add-back. | E9: Line relabelled; stays net negative (-1% of revenue), so there is no SBC add-back in the FCF. | F9: Confirmed
A10: 6 | B10: DCF - taxes | C10: Tax on EBIT, excluding the interest tax shield (DCF Key Rule #4). | D10: EBIT x 22%. | E10: No change. | F10: Confirmed
A11: 7 | B11: DCF - leases | C11: If rent is deducted in FCF, do not deduct lease liabilities in the bridge (DCF Key Rules #6, #13). | D11: Rent in FCF, leases excluded from net debt and WACC. | E11: No change; lease liability shown as a memo only. | F11: Confirmed
A12: 8 | B12: DCF - stub & mid-year | C12: Count only cash flow not yet generated; mid-year convention is more accurate; TV discounted half a year earlier with the perpetuity method (DCF Key Rule #11). | D12: Stub counted from price date against FY25 year-end net debt; year-end discounting. | E12: FY26 H2 cash flow counted against the 30-Jun-2026 balance sheet; mid-year switch (on) with the guide's stub mechanics. | F12: Changed
A13: 9 | B13: Bridge - latest balance sheet | C13: Update the EV bridge to the most recent interim balance sheet (Multiples Key Rule #15). | D13: FY25 year-end cash and debt. | E13: 30-Jun-2026 10-Q: cash $822m, debt $39,863m carrying / $38,300m fair value. | F13: Changed
A14: 10 | B14: Bridge - market value of debt | C14: Use market / fair values of debt where available (Multiples Key Rule #10). | D14: Book debt. | E14: Fair value of debt ($38.3bn) used in the bridge and WACC weights. | F14: Changed
A15: 11 | B15: Per share - diluted shares | C15: Use diluted shares (treasury stock method) (Multiples Key Rule #2). | D15: Basic 707.6m shares. | E15: 709.6m = 707.6m basic + 2.0m TSM dilution (10-Q Q2-26). | F15: Changed
A16: 12 | B16: WACC - beta | C16: Banks go beyond historical beta: un-lever peer betas, re-lever at current and target structure, use a range (DCF Key Rule #5). | D16: Blume-adjusted historical beta only (0.60) -> WACC 7.47%. | E16: Three methods (historical; peer re-levered at current D/E; peer re-levered at peer-median D/Cap); WACC = average. Leases excluded from D/E. | F16: Changed
... A24: 20 | B24: Data gap | C24: Peer lease data from filings. | D24: n/a | E24: SBUX Jun-2026 operating lease liability is an estimate (~$9.0bn); it does not affect the median. | F24: Flagged
A26: ROUND 2 - EXTERNAL FEEDBACK REVIEW (25-Sep-2026): what was raised, whether it was right, what changed
A27: # | B27: Feedback point | C27: Assessment (accurate? relevant to the model?) | D27: Before | E27: Change made | F27: Status
A28: 21 | B28: Share price timestamp | C28: Accurate. Official 24-Sep close was $237.02 (open $239.70, range $237.02-$242.56; Stock Analysis / S&P Global history). Relevant: every price-derived metric moves. | D28: $240.09 at 9:56am ET; yield 3.22% from the source. | E28: Price = close (Market_WACC B6); yield = $7.72 / price; MCD source multiples rescaled to the close (Peers rows 13, 24). | F28: Changed
A29: 22 | B29: Peer price timestamps (not raised) | C29: Found during this review: QSR and DPZ at the 23-Sep close, YUM / SBUX / CMG at 24-Sep morning prints. | D29: Mixed timestamps. | E29: Not changed: consistent closes were not retrievable from the same source. Documented on Peers; a 1% move in both peer multiples moves the comps value ~$3/share. RESOLVED 26-Sep (round 5): peers moved to 24-Sep closes. | F29: Resolved (round 5)
A30: 23 | B30: Comps: 40% weight on a peer set the report called distorted | C30: Accurate, and the most important point. The report said franchise-heavy peers fit better (~$251) yet used all five ($293). | D30: All-peer median $292.69. | E30: Franchise-heavy median (YUM, QSR, DPZ) is the comps leg; range = min / max; all-five kept as memo (Comps row 34). | F30: Changed
A31: 24 | B31: Comps without growth context | C31: Valid: multiples alone cannot show whether a discount is deserved. | D31: None. | E31: Peer growth and business-model table (Comps rows 39-48): QSR / DPZ imply ~14-15% NTM EPS growth vs ~7% for MCD. | F31: Added
A32: 25 | B32: Historical financial analysis thin | C32: Valid: history was financial totals only, no operating drivers. | D32: Historical_5Y only. | E32: New Historical_Drivers tab: comps, units, systemwide sales, take rates, margins, SG&A, FCF conversion, reported ROIC, leverage, coverage. | F32: Added
A33: 26 | B33: FCF terminology (UFCF vs company FCF conversion) | C33: Valid. | D33: UFCF and "levered FCF / adj. NI" shown without a clear distinction. | E33: Rows relabelled; company-definition conversion (FCF / GAAP NI) added (Forecast rows 48-49). | F33: Changed
A34: 27 | B34: GAAP-to-adjusted bridge | C34: Valid. | D34: None. | E34: Historical_Drivers rows 40-51; ties to reported $12,003m / $12,621m and $11.72 / $12.20 / $6.21. | F34: Added
A35: 28 | B35: Independent industry and franchisee evidence | C35: Valid: industry view relied on management commentary. | D35: Company sources only. | E35: Industry_Evidence tab (RMS, Black Box, NRA, BLS, Circana, Placer.ai) plus franchisee unit economics from Investor Day. | F35: Added
A36: 29 | B36: WACC: averaging three methods | C36: Partly valid - a judgment, not an error. Using franchise-heavy peers alone would cut WACC to ~7.2% (cost of equity ~2.6pp over Treasuries) and flip the rating to Buy on a method choice. | D36: Average of three methods (8.04%). | E36: Kept as base. Valuation rows 52-59 show DCF, target and rating under each method. SUPERSEDED 26-Sep by the beta note: see rows 53+. | F36: Superseded (round 3)
A37: 30 | B37: Beta 0.41 vs 0.60 / 0.81 / 0.86 | C37: Valid presentation point. | D37: Unexplained. | E37: Reconciliation on WACC rows 44-49. | F37: Changed
A38: 31 | B38: Consensus estimates | C38: Valid (data collection). | D38: Street target only. | E38: Valuation rows 61-66: implied consensus NTM EPS vs model; Street mean target. | F38: Added
A39: 32 | B39: DCF exit-multiple check | C39: Follows from the comps change. | D39: vs all-peer median. | E39: DCF B61 now vs the franchise-heavy median. | F39: Changed
A40: 33 | B40: "14 cents" wording, Figure 6, page density, ESG, "does not need traffic" | C40: Reasonable, but they concern the six-page report / deck, not this model. | D40: n/a | E40: Apply in the report and deck. The model already defines the take rate per franchised sales dollar (Historical_Drivers row 20). | F40: Not for model
A43: TARGET BRIDGE - previous file to this version ($ per share)
B44: Target in the previous file (typed) | D44: 251.08 | E44: Previous version: 0.6 x $223.34 + 0.4 x $292.69.
B45: Comps: all-five median -> franchise-heavy median (40% weight) | D45: -16.8528 | E45: Largest change.
B46: DCF: WACC equity weight at the close (60% weight) | D46: 0.0871 | E46: Typed: round-2 values frozen so this bridge stays a record of that step.
B47: Target after round 2 (typed) | D47: 234.3133
B48: Check: previous + changes - this version (should be 0) | D48: =D44+D45+D46-D47 -> 0.001
A51: ROUND 3 - BETA TREATMENT NOTE (26-Sep-2026): what it recommends, whether it is right, what changed
A52: # | B52: Recommendation | C52: Assessment (accurate? relevant to the model?) | D52: Before | E52: Change made | F52: Status
A53: 34 | B53: Primary beta = bottom-up, franchise-heavy peers, mean (~0.60) | C53: Accurate. The model reproduces it (mean unlevered 0.51 x relevering factor 1.18 = 0.61) and it matches MCD's own Blume-adjusted beta (0.60): two independent routes agree. It also answers the 25-Sep feedback point on WACC. | D53: Equal-weight average of three WACC methods: 8.03%. | E53: WACC = primary bottom-up beta (WACC rows 44-50, B39); all other estimates are sensitivities (rows 52-64). | F53: Changed
A54: 35 | B54: Stop equal-weighting three methods | C54: Accurate: equal weights had no economic basis and hid a choice. | D54: Average of methods 1-3. | E54: Replaced; earlier base kept as a memo (WACC C64). | F54: Changed
A55: 36 | B55: Mean rather than median for three peers | C55: Reasonable judgement: the median (0.52) is just YUM and ignores DPZ's supply-chain risk. | D55: n/a | E55: Mean used; median is the low case (WACC row 54). | F55: Changed
A56: 37 | B56: Unlever with market D/E, not net debt/EBITDA; exclude operating leases | C56: Accurate; the model already did both. Remaining gap: peers are unlevered with net debt while MCD is relevered at gross fair-value debt (gross peer debt not captured on one date). Effect < 0.01 on beta. | D56: Same. | E56: No change; documented (WACC row 72). | F56: Flagged
A57: 38 | B57: All-comps 0.79-0.81 as high case; never the raw 0.94 median | C57: Accurate: model gives 0.80 (mean) / 0.81 (median); the raw 0.94 (= CMG) was never used directly. | D57: 0.81 was method 2. | E57: High case in the sensitivity table. | F57: Changed
A58: 39 | B58: "8.04% cannot be rebuilt from published inputs (implies ~8.13%)" | C58: Not accurate: method 3 uses the peer-median debt / capital of 23%, not 18%. With that weight the three WACCs are 7.48 / 8.34 / 8.28% and average 8.03-8.04%. The report should have shown per-method weights. | D58: n/a | E58: No model change (moot after the switch). | F58: Not accurate
A59: 40 | B59: Same-date market data for D/E and betas | C59: Valid: peer market caps are 23-24 Sep snapshots (see #22). | D59: Mixed. | E59: Not refreshed; flagged. RESOLVED 26-Sep (round 5): peers moved to 24-Sep closes. | F59: Resolved (round 5)
A60: 41 | B60: Damodaran restaurant sector beta (~0.92) as outer bound | C60: Useful cross-check; figure taken from the note, not verified here. | D60: None. | E60: Added (WACC row 63). | F60: Added
A61: 42 | B61: Franchise-heavy = >= 90% of restaurants franchised; peer mix figures | C61: Reasonable analytical threshold; YUM ~97%, DPZ ~99%, SBUX China licensing taken from the note (citing 10-Ks), not re-verified. | D61: Qualitative labels. | E61: Added to Comps notes (rows 41-45). | F61: Added
A62: 43 | B62: Report wording and footnote for beta | C62: Applied in the Doc and the deck. | D62: "WACC: average of three methods". | E62: Rewritten. | F62: Changed
A64: TARGET BRIDGE - round 2 to round 3 ($ per share)
B65: Target after round 2 (typed) | D65: 234.3133
B66: DCF: WACC 8.03% -> primary beta WACC (60% weight) | D66: 17.6994 | E66: Round-2 DCF $223.49 inside the formula for traceability.
B67: Target after round 3 (typed) | D67: 252.0126
B68: Check (should be 0) | D68: =D65+D66-D67 -> 0.0001
A70: ROUND 4 - FOUR FINAL POINTS (26-Sep-2026): assessment and changes
A71: # | B71: Feedback point | C71: Assessment (accurate? relevant?) | D71: Before | E71: Change made | F71: Status
A72: 44 | B72: Figure 10: MCD row shows "0.60 WACC" in the unlevered-beta column | C72: Accurate: 0.60 is a relevered equity beta. Comparable MCD unlevered beta (from raw, like the peers) is 0.35; from the adjusted beta 0.51. | D72: 0.41 / "0.60 WACC" | E72: Beta column "0.41 raw / 0.60 adj."; unlevered cell 0.35 (WACC rows 74-77). | F72: Changed
A73: 45 | B73: Rating bands not exact ("+10 to 15%") | C73: Accurate: pages 4-5 and Figure 14 already used 10% as the Buy line. | D73: Buy-watch 10-15%, Buy 15%+ | E73: Buy >= +10%; Hold > -10% and < +10%; Sell <= -10% (Valuation B48, B50 and all rating formulas). | F73: Changed
A74: 46 | B74: Risk-free rate dated 23-Sep while the price is the 24-Sep close | C74: Accurate: 10-year was 5.11% (23-Sep) and 5.18% (24-Sep), per FRED DGS10 / H.15. Small, but the WACC is shown to two decimals. | D74: 5.10% (23-Sep) | E74: 5.18% at the 24-Sep close; cost of debt (UST + 90bp) moves with it. | F74: Changed
A75: 47 | B75: Justify the 50/50 P/E vs EV/EBITDA weighting | C75: Accurate: $225 vs $276 is a wide spread and the choice was unexplained. | D75: No justification | E75: Rationale in Comps P31; single-multiple targets in Valuation rows 89-92. | F75: Added
A77: TARGET BRIDGE - round 3 to round 4 ($ per share)
B78: Target after round 3 (typed) | D78: 252.0126
B79: DCF: risk-free 5.10% -> 5.18% (60% weight) | D79: -2.7178
B80: Target after round 4 (typed) | D80: 249.2948
B81: Check (should be 0) | D81: =D78+D79-D80 -> 0
A83: ROUND 5 - PEER PRICES SYNCHRONISED TO THE 24-SEP CLOSE (26-Sep-2026)
A84: # | B84: Feedback point | C84: Assessment (accurate? relevant?) | D84: Before | E84: Change made | F84: Status
A85: 48 | B85: Synchronise all peer market inputs to the 24-Sep close so "all market inputs as of 24 September" is literally true | C85: Accurate. QSR and DPZ were 23-Sep closes and YUM, SBUX, CMG 24-Sep morning prints, while the Doc and deck said all market inputs were at the 24-Sep close. 24-Sep closes verified on the Stock Analysis history pages (S&P Global): YUM 137.34, QSR 70.91, SBUX 93.65, CMG 32.01, DPZ 293.03. | D85: Mixed 23/24-Sep snapshot | E85: Peers rows 5-9 at the 24-Sep close; source snapshot kept in rows 29-33; multiples, market caps, EVs, D/E and unlevered betas flow through Comps and WACC. | F85: Changed
A87: TARGET BRIDGE - round 4 to round 5 ($ per share)
B88: Target after round 4 (typed) | D88: 249.2948
B89: Comps: peer multiples at the 24-Sep close (40% weight) | D89: =Valuation!B8*(Comps!D31-250.5538) -> -0.96722187
B90: DCF: beta and WACC at the 24-Sep close (60% weight) | D90: =Valuation!B7*(Valuation!B5-248.4555) -> 0.24997108
B91: Target in this version | D91: =Valuation!B9 -> 248.57757
B92: Check (should be 0) | D92: =D88+D89+D90-D91 -> -2e-05
A94: V6 TIDY-UP (26-Sep-2026)
B95: Removed Inputs, Analysis and Session1_Notes (unused Step-1 template and study notes; no other sheet referenced them) and the Step-2 starter WACC block on Market_WACC (7.23%, superseded by the WACC tab). README rebuilt. Valuation unchanged.
